Workbook

Sheet Leggimi
A1: Scenari Kalab × B2Brand — come usare questo foglio (aggiornato il 04/10/2026)
A3: Le celle AZZURRE sono ipotesi: cambiale e tutto il resto si ricalcola. Le celle VERDI sono i risultati da guardare.
A5: Cosa è cambiato il 04/10: costo vero delle creme (~1 € a vasetto, da Luciano); catalogo solo non deperibile (polveri, secco, creme, sott'olio, kit e box: semi, piantine e fresco a mix zero); obiettivo 1.000 € al mese; nuovo foglio Logistica. Poi, sempre il 04/10: le ore di B2Brand escono dai conti (sito e contenuti li fa Claude Code) e l'accordo diventa «metà del margine» (foglio Equilibrio); si torna alla percentuale fissa scrivendo «percentuale» nella cella Modello delle Ipotesi.
A7: Fogli:
A8: • Ipotesi — un «ordine tipo» per categoria: prezzo, IVA, costi, spedizione, commissioni, quota del mix. In fondo: percentuale di B2Brand, base di calcolo («netto» = merce senza IVA e senza commissioni, la spedizione passa a Kalab al costo; «lordo» = tutto l'incasso, IVA e spedizione comprese) e obiettivo mensile di B2Brand.
A9: • Conti per prodotto — per ogni ordine tipo: quanto va a B2Brand e quanto resta a Kalab dopo prodotto, imballo, spedizione e perdite (colonna O).
A10: • Costi B2Brand — i soldi che B2Brand anticipa e spende ogni mese (le ore non contano: lavora Claude Code). I video social non sono nell'accordo.
A11: • Stagionalità — peso di ogni mese (media = 1), da Google Trends e dai dati del Natale online.
A12: • Scenari — in alto le leve (ordini, pubblicità) e gli ordini al mese che servono per l'obiettivo; sotto, 36 mesi per scenario con il netto di B2Brand e di Kalab affiancati; in fondo il riepilogo.
A13: • Equilibrio — la percentuale della merce netta che dà la stessa cifra a B2Brand e Kalab, secondo i volumi, e quanto prende ciascuno.
A14: • Logistica — quanto costa a ordine la corsa pomeridiana all'hub contro un magazzino conto terzi vicino all'hub.
A15: • Confronto accordi — lo stesso ordine medio con percentuali e basi diverse.
... A20: • Il mese 1 del piano è marzo 2027. Si cambia in scenari/ipotesi.py (mese_avvio) e si rigenera con: python3 scenari/genera_xlsx.py

Sheet Ipotesi
A1: Categoria | B1: Prezzo medio al pubblico (€, IVA incl.) | C1: IVA % | D1: Costo prodotto (€) | E1: Imballo (€) | F1: Spedizione pagata dal cliente (€) | G1: Spedizione costo vero (€) | H1: Commissione pagamento % | I1: Commissione pagamento fissa (€) | J1: Tasso resi/perdite % | K1: Quota del mix ordini % | L1: Fonte / nota
A2: Polveri e secco (4 vasetti 12-15 g o 2 + sacchetti) | B2: 28 | C2: 0.1 | D2: 4 | E2: 0.8 | F2: 5.9 | G2: 7 | H2: 0.02 | I2: 0.25 | J2: 0.01 | K2: 0.3 | L2: Prezzi: Peperita 12 g 4,95-11,50 €, calabresi 50-100 g 3,50-6 € (ricerca 02/04). Costo STIMA ~1 €/vasetto, in linea col dato di Luciano sulle creme (04/10). Spedizione: secco 1 kg Italia 6-11 € a listino, 7 € con tariffa negoziata (03).
A3: Creme e salse (3 vasetti a 7,50 €) | B3: 22.5 | C3: 0.1 | D3: 3 | E3: 1.2 | F3: 5.9 | G3: 7.5 | H3: 0.02 | I3: 0.25 | J3: 0.02 | K3: 0.35 | L3: DATO KALAB: prezzo 7,50 €/crema (kalab.it); costo ~1 €/vasetto (Luciano, riferito da Davide il 04/10/2026).
A4: Sott'olio e conserve (2 vasetti + 1 crema) | B4: 24 | C4: 0.1 | D4: 4 | E4: 1.5 | F4: 5.9 | G4: 8 | H4: 0.02 | I4: 0.25 | J4: 0.02 | K4: 0.1 | L4: Prezzi 4,49-9 € a vasetto (02). Costo STIMA 1,5 €/vasetto (più olio delle creme; da chiedere a Luciano). Vetro pesante (1,5-2 kg): spedizione 8 € (03).
A5: Semi (4 bustine) | B5: 14 | C5: 0.1 | D5: 1.6 | E5: 0.3 | F5: 2.9 | G5: 3 | H5: 0.02 | I5: 0.25 | J5: 0.01 | K5: 0 | L5: Prezzi 1-5 €/bustina (02); costo STIMA 0,35 € (04). Plico postale. ATTENZIONE: vincolo legge sementiera (04 §4).
A6: Piantine (5 vasi, solo marzo-giugno) | B6: 25 | C6: 0.1 | D6: 10 | E6: 2.5 | F6: 8.9 | G6: 9.5 | H6: 0.02 | I6: 0.25 | J6: 0.08 | K6: 0 | L6: Prezzi 2,70-5 €/vaso (02); costo STIMA 1,5-2 € (04). Serve RUOP + passaporto piante. Resi alti: viva.
A7: Kit degustazione / box regalo | B7: 38 | C7: 0.1 | D7: 6 | E7: 2 | F7: 5.9 | G7: 7 | H7: 0.02 | I7: 0.25 | J7: 0.02 | K7: 0.25 | L7: Prezzi 25-45 € (02/04); costo STIMA 5 vasetti a ~1 € + astuccio. Picco nov-dic.
A8: Fresco 1 kg isotermico, solo Italia 24 h | B8: 20 | C8: 0.04 | D8: 4.5 | E8: 4 | F8: 9.9 | G8: 15 | H8: 0.02 | I8: 0.25 | J8: 0.1 | K8: 0 | L8: Prezzi 12-24 €/kg varietà nominate (02). Costo STIMA; imballo isotermico+gel STIMA 3-5 €; espresso 24 h 12-18 € negoziato (03 §costo a pacco: 17-25 € tutto compreso). Resi 10% = esperienza Natale scorso.
A10: Controllo: il mix deve fare 100% | K10: =SUM(K2:K8)
A12: Quota B2Brand sull'incasso (ipotesi base) | B12: 0.5 | C12: Il 50% proposto da Kalab. Cambiare qui per vedere l'effetto ovunque.
A13: Base di calcolo della quota | B13: netto | C13: "lordo" = sull'incasso IVA inclusa; "netto" = incasso senza IVA, senza spedizione incassata, senza commissioni di pagamento
A14: Obiettivo B2Brand: euro di cassa al mese | B14: 1000 | C14: Quota incassata meno spese vive e pubblicità, prima delle tasse. Le ore di B2Brand sono a parte (foglio Scenari, colonne «costo pieno»).
A15: Modello di accordo | B15: margine | C15: "margine" = metà a testa di quello che resta dopo prodotto, imballo, spedizione, commissioni, pubblicità e piattaforma (B2Brand anticipa e si riprende per prima i costi); "percentuale" = B2Brand prende la quota qui sopra e paga lei pubblicità e piattaforma

Sheet Conti per prodotto
A1: Categoria | B1: Prezzo pubblico | C1: IVA | D1: Netto IVA | E1: Spedizione incassata | F1: Commissioni pagamento | G1: Incasso netto (base 'netto') | H1: Base di calcolo quota | I1: Quota B2Brand (€) | J1: Resta a Kalab (lordo) | K1: Costo prodotto | L1: Imballo | M1: Spedizione vera | N1: Perdite per resi | O1: Margine Kalab (€) | P1: Margine Kalab % sul prezzo | Q1: Margine Kalab % sul suo incasso
A2: =Ipotesi!A2 | B2: =Ipotesi!B2 | C2: =B2-B2/(1+Ipotesi!C2) | D2: =B2-C2 | E2: =Ipotesi!F2 | F2: =(B2+E2)*Ipotesi!H2+Ipotesi!I2 | G2: =D2-F2 | H2: =IF(Ipotesi!$B$13="lordo",B2+E2,G2) | I2: =H2*Ipotesi!$B$12 | J2: =D2+E2-F2-I2 | K2: =Ipotesi!D2 | L2: =Ipotesi!E2 | M2: =Ipotesi!G2 | N2: =(B2+Ipotesi!G2)*Ipotesi!J2 | O2: =J2-K2-L2-M2-N2 | P2: =O2/B2 | Q2: =IF(J2=0,0,O2/J2)
A3: =Ipotesi!A3 | B3: =Ipotesi!B3 | C3: =B3-B3/(1+Ipotesi!C3) | D3: =B3-C3 | E3: =Ipotesi!F3 | F3: =(B3+E3)*Ipotesi!H3+Ipotesi!I3 | G3: =D3-F3 | H3: =IF(Ipotesi!$B$13="lordo",B3+E3,G3) | I3: =H3*Ipotesi!$B$12 | J3: =D3+E3-F3-I3 | K3: =Ipotesi!D3 | L3: =Ipotesi!E3 | M3: =Ipotesi!G3 | N3: =(B3+Ipotesi!G3)*Ipotesi!J3 | O3: =J3-K3-L3-M3-N3 | P3: =O3/B3 | Q3: =IF(J3=0,0,O3/J3)
A4: =Ipotesi!A4 | B4: =Ipotesi!B4 | C4: =B4-B4/(1+Ipotesi!C4) | D4: =B4-C4 | E4: =Ipotesi!F4 | F4: =(B4+E4)*Ipotesi!H4+Ipotesi!I4 | G4: =D4-F4 | H4: =IF(Ipotesi!$B$13="lordo",B4+E4,G4) | I4: =H4*Ipotesi!$B$12 | J4: =D4+E4-F4-I4 | K4: =Ipotesi!D4 | L4: =Ipotesi!E4 | M4: =Ipotesi!G4 | N4: =(B4+Ipotesi!G4)*Ipotesi!J4 | O4: =J4-K4-L4-M4-N4 | P4: =O4/B4 | Q4: =IF(J4=0,0,O4/J4)
A5: =Ipotesi!A5 | B5: =Ipotesi!B5 | C5: =B5-B5/(1+Ipotesi!C5) | D5: =B5-C5 | E5: =Ipotesi!F5 | F5: =(B5+E5)*Ipotesi!H5+Ipotesi!I5 | G5: =D5-F5 | H5: =IF(Ipotesi!$B$13="lordo",B5+E5,G5) | I5: =H5*Ipotesi!$B$12 | J5: =D5+E5-F5-I5 | K5: =Ipotesi!D5 | L5: =Ipotesi!E5 | M5: =Ipotesi!G5 | N5: =(B5+Ipotesi!G5)*Ipotesi!J5 | O5: =J5-K5-L5-M5-N5 | P5: =O5/B5 | Q5: =IF(J5=0,0,O5/J5)
A6: =Ipotesi!A6 | B6: =Ipotesi!B6 | C6: =B6-B6/(1+Ipotesi!C6) | D6: =B6-C6 | E6: =Ipotesi!F6 | F6: =(B6+E6)*Ipotesi!H6+Ipotesi!I6 | G6: =D6-F6 | H6: =IF(Ipotesi!$B$13="lordo",B6+E6,G6) | I6: =H6*Ipotesi!$B$12 | J6: =D6+E6-F6-I6 | K6: =Ipotesi!D6 | L6: =Ipotesi!E6 | M6: =Ipotesi!G6 | N6: =(B6+Ipotesi!G6)*Ipotesi!J6 | O6: =J6-K6-L6-M6-N6 | P6: =O6/B6 | Q6: =IF(J6=0,0,O6/J6)
A7: =Ipotesi!A7 | B7: =Ipotesi!B7 | C7: =B7-B7/(1+Ipotesi!C7) | D7: =B7-C7 | E7: =Ipotesi!F7 | F7: =(B7+E7)*Ipotesi!H7+Ipotesi!I7 | G7: =D7-F7 | H7: =IF(Ipotesi!$B$13="lordo",B7+E7,G7) | I7: =H7*Ipotesi!$B$12 | J7: =D7+E7-F7-I7 | K7: =Ipotesi!D7 | L7: =Ipotesi!E7 | M7: =Ipotesi!G7 | N7: =(B7+Ipotesi!G7)*Ipotesi!J7 | O7: =J7-K7-L7-M7-N7 | P7: =O7/B7 | Q7: =IF(J7=0,0,O7/J7)
A8: =Ipotesi!A8 | B8: =Ipotesi!B8 | C8: =B8-B8/(1+Ipotesi!C8) | D8: =B8-C8 | E8: =Ipotesi!F8 | F8: =(B8+E8)*Ipotesi!H8+Ipotesi!I8 | G8: =D8-F8 | H8: =IF(Ipotesi!$B$13="lordo",B8+E8,G8) | I8: =H8*Ipotesi!$B$12 | J8: =D8+E8-F8-I8 | K8: =Ipotesi!D8 | L8: =Ipotesi!E8 | M8: =Ipotesi!G8 | N8: =(B8+Ipotesi!G8)*Ipotesi!J8 | O8: =J8-K8-L8-M8-N8 | P8: =O8/B8 | Q8: =IF(J8=0,0,O8/J8)
A10: Medie pesate sul mix ordini | B10: =SUMPRODUCT(B2:B8,Ipotesi!K2:K8) | G10: =SUMPRODUCT(G2:G8,Ipotesi!K2:K8) | H10: =SUMPRODUCT((B2:B8+E2:E8),Ipotesi!K2:K8) | I10: =SUMPRODUCT(I2:I8,Ipotesi!K2:K8) | L10: =SUMPRODUCT(L2:L8,Ipotesi!K2:K8) | M10: =SUMPRODUCT(M2:M8,Ipotesi!K2:K8) | O10: =SUMPRODUCT(O2:O8,Ipotesi!K2:K8) | P10: =O10/B10
A11: Letture: colonna O = quanto resta a Kalab per ordine dopo prodotto, imballo, spedizione e quota B2Brand. Se è vicino a zero o negativo, con quella quota Kalab lavora gratis.
A12: Medie pesate: G = incassato netto medio per ordine; H = incasso lordo medio (merce + spedizione); L = imballo medio; M = spedizione vera media.

Sheet Costi B2Brand
A1: Voce | B1: Una tantum (€) | C1: Mensile anno 1 (€) | D1: Mensile anno 2 (€) | E1: Mensile anno 3 (€) | F1: Fonte / nota | G1: Tipo (cassa = soldi che escono; ore = tempo di B2Brand a 35 €/h)
A2: Avvio: tema, dominio, app, campioni e prove di spedizione | B2: 500 | C2: 0 | D2: 0 | E2: 0 | F2: STIMA. Costruzione, testi e traduzioni: Claude Code (abbonamento già pagato da B2Brand). | G2: cassa
A3: Foto prodotto | B3: 0 | C3: 0 | D3: 0 | E3: 0 | F3: Da decidere: foto in azienda quando Davide scende per i video. I video social NON sono nell'accordo (mai discussi). | G3: cassa
A4: Piattaforma + app + dominio | B4: 0 | C4: 100 | D4: 120 | E4: 150 | F4: Shopify Basic 27 €/mese + app 50-150 € (07 B2, listino Shopify 02/10/2026). | G4: cassa
A5: TOTALE | B5: =SUM(B2:B4) | C5: =SUM(C2:C4) | D5: =SUM(D2:D4) | E5: =SUM(E2:E4)
A6: di cui SOLO CASSA | B6: =SUMIF($G$2:$G$4,"cassa",B2:B4) | C6: =SUMIF($G$2:$G$4,"cassa",C2:C4) | D6: =SUMIF($G$2:$G$4,"cassa",D2:D4) | E6: =SUMIF($G$2:$G$4,"cassa",E2:E4)
A7: Nel foglio Scenari le spese vive (cassa) e le ore sono in colonne separate: «netto di cassa» = soldi in tasca; «costo pieno» = anche le ore pagate a 35 €/h.

Sheet Stagionalità
A1: Mese | B1: Peso del mese (media = 1,00) | C1: Nota | D1: Mese del piano nell'anno (1 = mese di avvio) | E1: Mese del piano × peso
A2: gen | B2: 0.85 | C2: dopo Natale; semi iniziano | D2: 11 | E2: =D2*B2
A3: feb | B3: 0.95 | C3: semi (Trends IT picco feb-mar) | D3: 12 | E3: =D3*B3
A4: mar | B4: 1 | C4: semi + piantine | D4: 1 | E4: =D4*B4
A5: apr | B5: 0.95 | C5: piantine (Trends: apr-mag) | D5: 2 | E5: =D5*B5
A6: mag | B6: 0.85 | C6: piantine | D6: 3 | E6: =D6*B6
A7: giu | B7: 0.65 | C7: estate: minimo (Trends giu-lug) | D7: 4 | E7: =D7*B7
A8: lug | B8: 0.65 | C8: minimo | D8: 5 | E8: =D8*B8
A9: ago | B9: 0.75 | C9: raccolta: ricerche al massimo ma si compra in azienda/sagre | D9: 6 | E9: =D9*B9
A10: set | B10: 1 | C10: Festival Diamante 9-13/9; raccolta | D10: 7 | E10: =D10*B10
A11: ott | B11: 1 | C11: secco nuovo; inizio regali | D11: 8 | E11: =D11*B11
A12: nov | B12: 1.35 | C12: Black Friday; picco 'sauce piquante' FR | D12: 9 | E12: =D12*B12
A13: dic | B13: 2 | C13: Natale: picco acquisti online 5 e 16-17 dic (idealo) | D13: 10 | E13: =D13*B13
A14: Somma (deve fare 12) | B14: =SUM(B2:B13) | D14: Fattore di crescita (somma ÷ 12) | E14: =SUM(E2:E13)/12

Sheet Scenari
A1: Ipotesi per scenario (celle azzurre)
A2: Parametro | B2: Prudente | C2: Medio | D2: Ambizioso | E2: Nota
A3: Ordini al mese a regime, anno 1 (dopo la rampa) | B3: 20 | C3: 50 | D3: 100 | E3: STIMA. Oggi kalab.it ha 13 prodotti e ~10 pagine indicizzate: si parte da zero. 500 €/mese di pubblicità danno 10-17 ordini (05 §5.2); il resto da SEO, newsletter, eventi.
A4: Ordini al mese, media anno 2 | B4: 40 | C4: 120 | D4: 250 | E4: STIMA. Anno 2: schede varietà indicizzate, recensioni, secondo Natale, Germania aperta.
A5: Ordini al mese, media anno 3 | B5: 60 | C5: 200 | D5: 450 | E5: STIMA. Anno 3: catalogo completo, 3-4 lingue, B2B (Ankorstore/Faire) fuori da questo conto.
A6: Mesi di rampa prima del regime (anno 1) | B6: 6 | C6: 6 | D6: 6 | E6: Mesi per arrivare a regime nel primo anno (crescita lineare).
A7: Budget pubblicità mensile anno 1 (€, pagato da B2Brand) | B7: 300 | C7: 400 | D7: 500 | E7: Pagata da B2Brand. Sotto 300 €/mese Google Shopping non impara (05 §5).
A8: Budget pubblicità mensile anno 2 (€) | B8: 300 | C8: 600 | D8: 1000
A9: Budget pubblicità mensile anno 3 (€) | B9: 300 | C9: 800 | D9: 1500
A10: Ordini al mese necessari per l'obiettivo, anno 1 | B10: =ROUND(IF(Ipotesi!$B$15="margine",(2*Ipotesi!$B$14+'Costi B2Brand'!$C$6+B$7)/('Conti per prodotto'!$O$10+'Conti per prodotto'!$I$10),(Ipotesi!$B$14+'Costi B2Brand'!$C$6+B$7)/'Conti per prodotto'!$I$10),0) | C10: =ROUND(IF(Ipotesi!$B$15="margine",(2*Ipotesi!$B$14+'Costi B2Brand'!$C$6+C$7)/('Conti per prodotto'!$O$10+'Conti per prodotto'!$I$10),(Ipotesi!$B$14+'Costi B2Brand'!$C$6+C$7)/'Conti per prodotto'!$I$10),0) | D10: =ROUND(IF(Ipotesi!$B$15="margine",(2*Ipotesi!$B$14+'Costi B2Brand'!$C$6+D$7)/('Conti per prodotto'!$O$10+'Conti per prodotto'!$I$10),(Ipotesi!$B$14+'Costi B2Brand'!$C$6+D$7)/'Conti per prodotto'!$I$10),0) | E10: Con «margine» l'obiettivo vale per entrambi: B2Brand e Kalab prendono la stessa cifra.
A11: Ordini al mese necessari per l'obiettivo, anno 2 | B11: =ROUND(IF(Ipotesi!$B$15="margine",(2*Ipotesi!$B$14+'Costi B2Brand'!$D$6+B$8)/('Conti per prodotto'!$O$10+'Conti per prodotto'!$I$10),(Ipotesi!$B$14+'Costi B2Brand'!$D$6+B$8)/'Conti per prodotto'!$I$10),0) | C11: =ROUND(IF(Ipotesi!$B$15="margine",(2*Ipotesi!$B$14+'Costi B2Brand'!$D$6+C$8)/('Conti per prodotto'!$O$10+'Conti per prodotto'!$I$10),(Ipotesi!$B$14+'Costi B2Brand'!$D$6+C$8)/'Conti per prodotto'!$I$10),0) | D11: =ROUND(IF(Ipotesi!$B$15="margine",(2*Ipotesi!$B$14+'Costi B2Brand'!$D$6+D$8)/('Conti per prodotto'!$O$10+'Conti per prodotto'!$I$10),(Ipotesi!$B$14+'Costi B2Brand'!$D$6+D$8)/'Conti per prodotto'!$I$10),0)
A12: Ordini al mese necessari per l'obiettivo, anno 3 | B12: =ROUND(IF(Ipotesi!$B$15="margine",(2*Ipotesi!$B$14+'Costi B2Brand'!$E$6+B$9)/('Conti per prodotto'!$O$10+'Conti per prodotto'!$I$10),(Ipotesi!$B$14+'Costi B2Brand'!$E$6+B$9)/'Conti per prodotto'!$I$10),0) | C12: =ROUND(IF(Ipotesi!$B$15="margine",(2*Ipotesi!$B$14+'Costi B2Brand'!$E$6+C$9)/('Conti per prodotto'!$O$10+'Conti per prodotto'!$I$10),(Ipotesi!$B$14+'Costi B2Brand'!$E$6+C$9)/'Conti per prodotto'!$I$10),0) | D12: =ROUND(IF(Ipotesi!$B$15="margine",(2*Ipotesi!$B$14+'Costi B2Brand'!$E$6+D$9)/('Conti per prodotto'!$O$10+'Conti per prodotto'!$I$10),(Ipotesi!$B$14+'Costi B2Brand'!$E$6+D$9)/'Conti per prodotto'!$I$10),0)
A13: Tendenza a fine anno 2 (ordini al mese senza stagionalità) | B13: =B$3+(B$4*12-B$3*Stagionalità!$B$14)/Stagionalità!$E$14 | C13: =C$3+(C$4*12-C$3*Stagionalità!$B$14)/Stagionalità!$E$14 | D13: =D$3+(D$4*12-D$3*Stagionalità!$B$14)/Stagionalità!$E$14 | E13: Crescita continua: dalla fine dell'anno 1 gli ordini salgono in linea retta, con lo stesso totale annuo di «media × 12». Niente salti a marzo.
A14: Tendenza a fine anno 3 (ordini al mese senza stagionalità) | B14: =B$13+(B$5*12-B$13*Stagionalità!$B$14)/Stagionalità!$E$14 | C14: =C$13+(C$5*12-C$13*Stagionalità!$B$14)/Stagionalità!$E$14 | D14: =D$13+(D$5*12-D$13*Stagionalità!$B$14)/Stagionalità!$E$14
A15: Proiezione mese per mese (formule). Netto = soldi in tasca, prima delle tasse.
A16: Prudente | Q16: Medio | AG16: Ambizioso
A17: Mese | B17: Anno | C17: Ordini | D17: Vendite online (€) | E17: Margine da dividere (€) | F17: Spese B2Brand (€) | G17: Pubblicità (€) | H17: Da recuperare per B2Brand (€) | I17: Versato a B2Brand (€) | J17: Netto B2Brand (€) | K17: Cumulato B2Brand (€) | L17: Netto Kalab (€) | M17: Cumulato Kalab (€) | N17: (appoggio) mese a quota obiettivo | O17: (appoggio) mese B2Brand in attivo | Q17: Mese | R17: Anno | S17: Ordini | T17: Vendite online (€) | U17: Margine da dividere (€) | V17: Spese B2Brand (€) | W17: Pubblicità (€) | X17: Da recuperare per B2Brand (€) | Y17: Versato a B2Brand (€) | Z17: Netto B2Brand (€) | AA17: Cumulato B2Brand (€) | AB17: Netto Kalab (€) | AC17: Cumulato Kalab (€) | AD17: (appoggio) mese a quota obiettivo | AE17: (appoggio) mese B2Brand in attivo | AG17: Mese | AH17: Anno | AI17: Ordini | AJ17: Vendite online (€) | AK17: Margine da dividere (€) | AL17: Spese B2Brand (€) | AM17: Pubblicità (€) | AN17: Da recuperare per B2Brand (€) | AO17: Versato a B2Brand (€) | AP17: Netto B2Brand (€) | AQ17: Cumulato B2Brand (€) | AR17: Netto Kalab (€) | AS17: Cumulato Kalab (€) | AT17: (appoggio) mese a quota obiettivo | AU17: (appoggio) mese B2Brand in attivo
A18: 1 | B18: 1 | C18: =ROUND(B$3*MIN(1,1/B$6)*Stagionalità!$B$4,0) | D18: =C18*'Conti per prodotto'!$B$10 | E18: =C18*('Conti per prodotto'!$O$10+'Conti per prodotto'!$I$10) | F18: ='Costi B2Brand'!$C$6+'Costi B2Brand'!$B$6 | G18: =B$7 | H18: =0 | I18: =IF(Ipotesi!$B$15="margine",MIN(E18,F18+G18+H18+0.5*MAX(0,(E18-F18-G18)-H18)),C18*'Conti per prodotto'!$I$10) | J18: =I18-F18-G18 | K18: =J18 | L18: =E18-I18 | M18: =L18 | N18: =IF(IF(Ipotesi!$B$15="margine",(E18-F18-G18)/2,J18)>=Ipotesi!$B$14,A18,"") | O18: =IF(AND(A18>1,K18>=0),A18,"") | Q18: 1 | R18: 1 | S18: =ROUND(C$3*MIN(1,1/C$6)*Stagionalità!$B$4,0) | T18: =S18*'Conti per prodotto'!$B$10 | U18: =S18*('Conti per prodotto'!$O$10+'Conti per prodotto'!$I$10) | V18: ='Costi B2Brand'!$C$6+'Costi B2Brand'!$B$6 | W18: =C$7 | X18: =0 | Y18: =IF(Ipotesi!$B$15="margine",MIN(U18,V18+W18+X18+0.5*MAX(0,(U18-V18-W18)-X18)),S18*'Conti per prodotto'!$I$10) | Z18: =Y18-V18-W18 | AA18: =Z18 | AB18: =U18-Y18 | AC18: =AB18 | AD18: =IF(IF(Ipotesi!$B$15="margine",(U18-V18-W18)/2,Z18)>=Ipotesi!$B$14,Q18,"") | AE18: =IF(AND(Q18>1,AA18>=0),Q18,"") | AG18: 1 | AH18: 1 | AI18: =ROUND(D$3*MIN(1,1/D$6)*Stagionalità!$B$4,0) | AJ18: =AI18*'Conti per prodotto'!$B$10 | AK18: =AI18*('Conti per prodotto'!$O$10+'Conti per prodotto'!$I$10) | AL18: ='Costi B2Brand'!$C$6+'Costi B2Brand'!$B$6 | AM18: =D$7 | AN18: =0 | AO18: =IF(Ipotesi!$B$15="margine",MIN(AK18,AL18+AM18+AN18+0.5*MAX(0,(AK18-AL18-AM18)-AN18)),AI18*'Conti per prodotto'!$I$10) | AP18: =AO18-AL18-AM18 | AQ18: =AP18 | AR18: =AK18-AO18 | AS18: =AR18 | AT18: =IF(IF(Ipotesi!$B$15="margine",(AK18-AL18-AM18)/2,AP18)>=Ipotesi!$B$14,AG18,"") | AU18: =IF(AND(AG18>1,AQ18>=0),AG18,"")
A19: 2 | B19: 1 | C19: =ROUND(B$3*MIN(1,2/B$6)*Stagionalità!$B$5,0) | D19: =C19*'Conti per prodotto'!$B$10 | E19: =C19*('Conti per prodotto'!$O$10+'Conti per prodotto'!$I$10) | F19: ='Costi B2Brand'!$C$6 | G19: =B$7 | H19: =IF(Ipotesi!$B$15="margine",MAX(0,H18-(E18-F18-G18)),0) | I19: =IF(Ipotesi!$B$15="margine",MIN(E19,F19+G19+H19+0.5*MAX(0,(E19-F19-G19)-H19)),C19*'Conti per prodotto'!$I$10) | J19: =I19-F19-G19 | K19: =K18+J19 | L19: =E19-I19 | M19: =M18+L19 | N19: =IF(IF(Ipotesi!$B$15="margine",(E19-F19-G19)/2,J19)>=Ipotesi!$B$14,A19,"") | O19: =IF(AND(A19>1,K19>=0),A19,"") | Q19: 2 | R19: 1 | S19: =ROUND(C$3*MIN(1,2/C$6)*Stagionalità!$B$5,0) | T19: =S19*'Conti per prodotto'!$B$10 | U19: =S19*('Conti per prodotto'!$O$10+'Conti per prodotto'!$I$10) | V19: ='Costi B2Brand'!$C$6 | W19: =C$7 | X19: =IF(Ipotesi!$B$15="margine",MAX(0,X18-(U18-V18-W18)),0) | Y19: =IF(Ipotesi!$B$15="margine",MIN(U19,V19+W19+X19+0.5*MAX(0,(U19-V19-W19)-X19)),S19*'Conti per prodotto'!$I$10) | Z19: =Y19-V19-W19 | AA19: =AA18+Z19 | AB19: =U19-Y19 | AC19: =AC18+AB19 | AD19: =IF(IF(Ipotesi!$B$15="margine",(U19-V19-W19)/2,Z19)>=Ipotesi!$B$14,Q19,"") | AE19: =IF(AND(Q19>1,AA19>=0),Q19,"") | AG19: 2 | AH19: 1 | AI19: =ROUND(D$3*MIN(1,2/D$6)*Stagionalità!$B$5,0) | AJ19: =AI19*'Conti per prodotto'!$B$10 | AK19: =AI19*('Conti per prodotto'!$O$10+'Conti per prodotto'!$I$10) | AL19: ='Costi B2Brand'!$C$6 | AM19: =D$7 | AN19: =IF(Ipotesi!$B$15="margine",MAX(0,AN18-(AK18-AL18-AM18)),0) | AO19: =IF(Ipotesi!$B$15="margine",MIN(AK19,AL19+AM19+AN19+0.5*MAX(0,(AK19-AL19-AM19)-AN19)),AI19*'Conti per prodotto'!$I$10) | AP19: =AO19-AL19-AM19 | AQ19: =AQ18+AP19 | AR19: =AK19-AO19 | AS19: =AS18+AR19 | AT19: =IF(IF(Ipotesi!$B$15="margine",(AK19-AL19-AM19)/2,AP19)>=Ipotesi!$B$14,AG19,"") | AU19: =IF(AND(AG19>1,AQ19>=0),AG19,"")
A20: 3 | B20: 1 | C20: =ROUND(B$3*MIN(1,3/B$6)*Stagionalità!$B$6,0) | D20: =C20*'Conti per prodotto'!$B$10 | E20: =C20*('Conti per prodotto'!$O$10+'Conti per prodotto'!$I$10) | F20: ='Costi B2Brand'!$C$6 | G20: =B$7 | H20: =IF(Ipotesi!$B$15="margine",MAX(0,H19-(E19-F19-G19)),0) | I20: =IF(Ipotesi!$B$15="margine",MIN(E20,F20+G20+H20+0.5*MAX(0,(E20-F20-G20)-H20)),C20*'Conti per prodotto'!$I$10) | J20: =I20-F20-G20 | K20: =K19+J20 | L20: =E20-I20 | M20: =M19+L20 | N20: =IF(IF(Ipotesi!$B$15="margine",(E20-F20-G20)/2,J20)>=Ipotesi!$B$14,A20,"") | O20: =IF(AND(A20>1,K20>=0),A20,"") | Q20: 3 | R20: 1 | S20: =ROUND(C$3*MIN(1,3/C$6)*Stagionalità!$B$6,0) | T20: =S20*'Conti per prodotto'!$B$10 | U20: =S20*('Conti per prodotto'!$O$10+'Conti per prodotto'!$I$10) | V20: ='Costi B2Brand'!$C$6 | W20: =C$7 | X20: =IF(Ipotesi!$B$15="margine",MAX(0,X19-(U19-V19-W19)),0) | Y20: =IF(Ipotesi!$B$15="margine",MIN(U20,V20+W20+X20+0.5*MAX(0,(U20-V20-W20)-X20)),S20*'Conti per prodotto'!$I$10) | Z20: =Y20-V20-W20 | AA20: =AA19+Z20 | AB20: =U20-Y20 | AC20: =AC19+AB20 | AD20: =IF(IF(Ipotesi!$B$15="margine",(U20-V20-W20)/2,Z20)>=Ipotesi!$B$14,Q20,"") | AE20: =IF(AND(Q20>1,AA20>=0),Q20,"") | AG20: 3 | AH20: 1 | AI20: =ROUND(D$3*MIN(1,3/D$6)*Stagionalità!$B$6,0) | AJ20: =AI20*'Conti per prodotto'!$B$10 | AK20: =AI20*('Conti per prodotto'!$O$10+'Conti per prodotto'!$I$10) | AL20: ='Costi B2Brand'!$C$6 | AM20: =D$7 | AN20: =IF(Ipotesi!$B$15="margine",MAX(0,AN19-(AK19-AL19-AM19)),0) | AO20: =IF(Ipotesi!$B$15="margine",MIN(AK20,AL20+AM20+AN20+0.5*MAX(0,(AK20-AL20-AM20)-AN20)),AI20*'Conti per prodotto'!$I$10) | AP20: =AO20-AL20-AM20 | AQ20: =AQ19+AP20 | AR20: =AK20-AO20 | AS20: =AS19+AR20 | AT20: =IF(IF(Ipotesi!$B$15="margine",(AK20-AL20-AM20)/2,AP20)>=Ipotesi!$B$14,AG20,"") | AU20: =IF(AND(AG20>1,AQ20>=0),AG20,"")
A21: 4 | B21: 1 | C21: =ROUND(B$3*MIN(1,4/B$6)*Stagionalità!$B$7,0) | D21: =C21*'Conti per prodotto'!$B$10 | E21: =C21*('Conti per prodotto'!$O$10+'Conti per prodotto'!$I$10) | F21: ='Costi B2Brand'!$C$6 | G21: =B$7 | H21: =IF(Ipotesi!$B$15="margine",MAX(0,H20-(E20-F20-G20)),0) | I21: =IF(Ipotesi!$B$15="margine",MIN(E21,F21+G21+H21+0.5*MAX(0,(E21-F21-G21)-H21)),C21*'Conti per prodotto'!$I$10) | J21: =I21-F21-G21 | K21: =K20+J21 | L21: =E21-I21 | M21: =M20+L21 | N21: =IF(IF(Ipotesi!$B$15="margine",(E21-F21-G21)/2,J21)>=Ipotesi!$B$14,A21,"") | O21: =IF(AND(A21>1,K21>=0),A21,"") | Q21: 4 | R21: 1 | S21: =ROUND(C$3*MIN(1,4/C$6)*Stagionalità!$B$7,0) | T21: =S21*'Conti per prodotto'!$B$10 | U21: =S21*('Conti per prodotto'!$O$10+'Conti per prodotto'!$I$10) | V21: ='Costi B2Brand'!$C$6 | W21: =C$7 | X21: =IF(Ipotesi!$B$15="margine",MAX(0,X20-(U20-V20-W20)),0) | Y21: =IF(Ipotesi!$B$15="margine",MIN(U21,V21+W21+X21+0.5*MAX(0,(U21-V21-W21)-X21)),S21*'Conti per prodotto'!$I$10) | Z21: =Y21-V21-W21 | AA21: =AA20+Z21 | AB21: =U21-Y21 | AC21: =AC20+AB21 | AD21: =IF(IF(Ipotesi!$B$15="margine",(U21-V21-W21)/2,Z21)>=Ipotesi!$B$14,Q21,"") | AE21: =IF(AND(Q21>1,AA21>=0),Q21,"") | AG21: 4 | AH21: 1 | AI21: =ROUND(D$3*MIN(1,4/D$6)*Stagionalità!$B$7,0) | AJ21: =AI21*'Conti per prodotto'!$B$10 | AK21: =AI21*('Conti per prodotto'!$O$10+'Conti per prodotto'!$I$10) | AL21: ='Costi B2Brand'!$C$6 | AM21: =D$7 | AN21: =IF(Ipotesi!$B$15="margine",MAX(0,AN20-(AK20-AL20-AM20)),0) | AO21: =IF(Ipotesi!$B$15="margine",MIN(AK21,AL21+AM21+AN21+0.5*MAX(0,(AK21-AL21-AM21)-AN21)),AI21*'Conti per prodotto'!$I$10) | AP21: =AO21-AL21-AM21 | AQ21: =AQ20+AP21 | AR21: =AK21-AO21 | AS21: =AS20+AR21 | AT21: =IF(IF(Ipotesi!$B$15="margine",(AK21-AL21-AM21)/2,AP21)>=Ipotesi!$B$14,AG21,"") | AU21: =IF(AND(AG21>1,AQ21>=0),AG21,"")
A22: 5 | B22: 1 | C22: =ROUND(B$3*MIN(1,5/B$6)*Stagionalità!$B$8,0) | D22: =C22*'Conti per prodotto'!$B$10 | E22: =C22*('Conti per prodotto'!$O$10+'Conti per prodotto'!$I$10) | F22: ='Costi B2Brand'!$C$6 | G22: =B$7 | H22: =IF(Ipotesi!$B$15="margine",MAX(0,H21-(E21-F21-G21)),0) | I22: =IF(Ipotesi!$B$15="margine",MIN(E22,F22+G22+H22+0.5*MAX(0,(E22-F22-G22)-H22)),C22*'Conti per prodotto'!$I$10) | J22: =I22-F22-G22 | K22: =K21+J22 | L22: =E22-I22 | M22: =M21+L22 | N22: =IF(IF(Ipotesi!$B$15="margine",(E22-F22-G22)/2,J22)>=Ipotesi!$B$14,A22,"") | O22: =IF(AND(A22>1,K22>=0),A22,"") | Q22: 5 | R22: 1 | S22: =ROUND(C$3*MIN(1,5/C$6)*Stagionalità!$B$8,0) | T22: =S22*'Conti per prodotto'!$B$10 | U22: =S22*('Conti per prodotto'!$O$10+'Conti per prodotto'!$I$10) | V22: ='Costi B2Brand'!$C$6 | W22: =C$7 | X22: =IF(Ipotesi!$B$15="margine",MAX(0,X21-(U21-V21-W21)),0) | Y22: =IF(Ipotesi!$B$15="margine",MIN(U22,V22+W22+X22+0.5*MAX(0,(U22-V22-W22)-X22)),S22*'Conti per prodotto'!$I$10) | Z22: =Y22-V22-W22 | AA22: =AA21+Z22 | AB22: =U22-Y22 | AC22: =AC21+AB22 | AD22: =IF(IF(Ipotesi!$B$15="margine",(U22-V22-W22)/2,Z22)>=Ipotesi!$B$14,Q22,"") | AE22: =IF(AND(Q22>1,AA22>=0),Q22,"") | AG22: 5 | AH22: 1 | AI22: =ROUND(D$3*MIN(1,5/D$6)*Stagionalità!$B$8,0) | AJ22: =AI22*'Conti per prodotto'!$B$10 | AK22: =AI22*('Conti per prodotto'!$O$10+'Conti per prodotto'!$I$10) | AL22: ='Costi B2Brand'!$C$6 | AM22: =D$7 | AN22: =IF(Ipotesi!$B$15="margine",MAX(0,AN21-(AK21-AL21-AM21)),0) | AO22: =IF(Ipotesi!$B$15="margine",MIN(AK22,AL22+AM22+AN22+0.5*MAX(0,(AK22-AL22-AM22)-AN22)),AI22*'Conti per prodotto'!$I$10) | AP22: =AO22-AL22-AM22 | AQ22: =AQ21+AP22 | AR22: =AK22-AO22 | AS22: =AS21+AR22 | AT22: =IF(IF(Ipotesi!$B$15="margine",(AK22-AL22-AM22)/2,AP22)>=Ipotesi!$B$14,AG22,"") | AU22: =IF(AND(AG22>1,AQ22>=0),AG22,"")
A23: 6 | B23: 1 | C23: =ROUND(B$3*MIN(1,6/B$6)*Stagionalità!$B$9,0) | D23: =C23*'Conti per prodotto'!$B$10 | E23: =C23*('Conti per prodotto'!$O$10+'Conti per prodotto'!$I$10) | F23: ='Costi B2Brand'!$C$6 | G23: =B$7 | H23: =IF(Ipotesi!$B$15="margine",MAX(0,H22-(E22-F22-G22)),0) | I23: =IF(Ipotesi!$B$15="margine",MIN(E23,F23+G23+H23+0.5*MAX(0,(E23-F23-G23)-H23)),C23*'Conti per prodotto'!$I$10) | J23: =I23-F23-G23 | K23: =K22+J23 | L23: =E23-I23 | M23: =M22+L23 | N23: =IF(IF(Ipotesi!$B$15="margine",(E23-F23-G23)/2,J23)>=Ipotesi!$B$14,A23,"") | O23: =IF(AND(A23>1,K23>=0),A23,"") | Q23: 6 | R23: 1 | S23: =ROUND(C$3*MIN(1,6/C$6)*Stagionalità!$B$9,0) | T23: =S23*'Conti per prodotto'!$B$10 | U23: =S23*('Conti per prodotto'!$O$10+'Conti per prodotto'!$I$10) | V23: ='Costi B2Brand'!$C$6 | W23: =C$7 | X23: =IF(Ipotesi!$B$15="margine",MAX(0,X22-(U22-V22-W22)),0) | Y23: =IF(Ipotesi!$B$15="margine",MIN(U23,V23+W23+X23+0.5*MAX(0,(U23-V23-W23)-X23)),S23*'Conti per prodotto'!$I$10) | Z23: =Y23-V23-W23 | AA23: =AA22+Z23 | AB23: =U23-Y23 | AC23: =AC22+AB23 | AD23: =IF(IF(Ipotesi!$B$15="margine",(U23-V23-W23)/2,Z23)>=Ipotesi!$B$14,Q23,"") | AE23: =IF(AND(Q23>1,AA23>=0),Q23,"") | AG23: 6 | AH23: 1 | AI23: =ROUND(D$3*MIN(1,6/D$6)*Stagionalità!$B$9,0) | AJ23: =AI23*'Conti per prodotto'!$B$10 | AK23: =AI23*('Conti per prodotto'!$O$10+'Conti per prodotto'!$I$10) | AL23: ='Costi B2Brand'!$C$6 | AM23: =D$7 | AN23: =IF(Ipotesi!$B$15="margine",MAX(0,AN22-(AK22-AL22-AM22)),0) | AO23: =IF(Ipotesi!$B$15="margine",MIN(AK23,AL23+AM23+AN23+0.5*MAX(0,(AK23-AL23-AM23)-AN23)),AI23*'Conti per prodotto'!$I$10) | AP23: =AO23-AL23-AM23 | AQ23: =AQ22+AP23 | AR23: =AK23-AO23 | AS23: =AS22+AR23 | AT23: =IF(IF(Ipotesi!$B$15="margine",(AK23-AL23-AM23)/2,AP23)>=Ipotesi!$B$14,AG23,"") | AU23: =IF(AND(AG23>1,AQ23>=0),AG23,"")
A24: 7 | B24: 1 | C24: =ROUND(B$3*MIN(1,7/B$6)*Stagionalità!$B$10,0) | D24: =C24*'Conti per prodotto'!$B$10 | E24: =C24*('Conti per prodotto'!$O$10+'Conti per prodotto'!$I$10) | F24: ='Costi B2Brand'!$C$6 | G24: =B$7 | H24: =IF(Ipotesi!$B$15="margine",MAX(0,H23-(E23-F23-G23)),0) | I24: =IF(Ipotesi!$B$15="margine",MIN(E24,F24+G24+H24+0.5*MAX(0,(E24-F24-G24)-H24)),C24*'Conti per prodotto'!$I$10) | J24: =I24-F24-G24 | K24: =K23+J24 | L24: =E24-I24 | M24: =M23+L24 | N24: =IF(IF(Ipotesi!$B$15="margine",(E24-F24-G24)/2,J24)>=Ipotesi!$B$14,A24,"") | O24: =IF(AND(A24>1,K24>=0),A24,"") | Q24: 7 | R24: 1 | S24: =ROUND(C$3*MIN(1,7/C$6)*Stagionalità!$B$10,0) | T24: =S24*'Conti per prodotto'!$B$10 | U24: =S24*('Conti per prodotto'!$O$10+'Conti per prodotto'!$I$10) | V24: ='Costi B2Brand'!$C$6 | W24: =C$7 | X24: =IF(Ipotesi!$B$15="margine",MAX(0,X23-(U23-V23-W23)),0) | Y24: =IF(Ipotesi!$B$15="margine",MIN(U24,V24+W24+X24+0.5*MAX(0,(U24-V24-W24)-X24)),S24*'Conti per prodotto'!$I$10) | Z24: =Y24-V24-W24 | AA24: =AA23+Z24 | AB24: =U24-Y24 | AC24: =AC23+AB24 | AD24: =IF(IF(Ipotesi!$B$15="margine",(U24-V24-W24)/2,Z24)>=Ipotesi!$B$14,Q24,"") | AE24: =IF(AND(Q24>1,AA24>=0),Q24,"") | AG24: 7 | AH24: 1 | AI24: =ROUND(D$3*MIN(1,7/D$6)*Stagionalità!$B$10,0) | AJ24: =AI24*'Conti per prodotto'!$B$10 | AK24: =AI24*('Conti per prodotto'!$O$10+'Conti per prodotto'!$I$10) | AL24: ='Costi B2Brand'!$C$6 | AM24: =D$7 | AN24: =IF(Ipotesi!$B$15="margine",MAX(0,AN23-(AK23-AL23-AM23)),0) | AO24: =IF(Ipotesi!$B$15="margine",MIN(AK24,AL24+AM24+AN24+0.5*MAX(0,(AK24-AL24-AM24)-AN24)),AI24*'Conti per prodotto'!$I$10) | AP24: =AO24-AL24-AM24 | AQ24: =AQ23+AP24 | AR24: =AK24-AO24 | AS24: =AS23+AR24 | AT24: =IF(IF(Ipotesi!$B$15="margine",(AK24-AL24-AM24)/2,AP24)>=Ipotesi!$B$14,AG24,"") | AU24: =IF(AND(AG24>1,AQ24>=0),AG24,"")
A25: 8 | B25: 1 | C25: =ROUND(B$3*MIN(1,8/B$6)*Stagionalità!$B$11,0) | D25: =C25*'Conti per prodotto'!$B$10 | E25: =C25*('Conti per prodotto'!$O$10+'Conti per prodotto'!$I$10) | F25: ='Costi B2Brand'!$C$6 | G25: =B$7 | H25: =IF(Ipotesi!$B$15="margine",MAX(0,H24-(E24-F24-G24)),0) | I25: =IF(Ipotesi!$B$15="margine",MIN(E25,F25+G25+H25+0.5*MAX(0,(E25-F25-G25)-H25)),C25*'Conti per prodotto'!$I$10) | J25: =I25-F25-G25 | K25: =K24+J25 | L25: =E25-I25 | M25: =M24+L25 | N25: =IF(IF(Ipotesi!$B$15="margine",(E25-F25-G25)/2,J25)>=Ipotesi!$B$14,A25,"") | O25: =IF(AND(A25>1,K25>=0),A25,"") | Q25: 8 | R25: 1 | S25: =ROUND(C$3*MIN(1,8/C$6)*Stagionalità!$B$11,0) | T25: =S25*'Conti per prodotto'!$B$10 | U25: =S25*('Conti per prodotto'!$O$10+'Conti per prodotto'!$I$10) | V25: ='Costi B2Brand'!$C$6 | W25: =C$7 | X25: =IF(Ipotesi!$B$15="margine",MAX(0,X24-(U24-V24-W24)),0) | Y25: =IF(Ipotesi!$B$15="margine",MIN(U25,V25+W25+X25+0.5*MAX(0,(U25-V25-W25)-X25)),S25*'Conti per prodotto'!$I$10) | Z25: =Y25-V25-W25 | AA25: =AA24+Z25 | AB25: =U25-Y25 | AC25: =AC24+AB25 | AD25: =IF(IF(Ipotesi!$B$15="margine",(U25-V25-W25)/2,Z25)>=Ipotesi!$B$14,Q25,"") | AE25: =IF(AND(Q25>1,AA25>=0),Q25,"") | AG25: 8 | AH25: 1 | AI25: =ROUND(D$3*MIN(1,8/D$6)*Stagionalità!$B$11,0) | AJ25: =AI25*'Conti per prodotto'!$B$10 | AK25: =AI25*('Conti per prodotto'!$O$10+'Conti per prodotto'!$I$10) | AL25: ='Costi B2Brand'!$C$6 | AM25: =D$7 | AN25: =IF(Ipotesi!$B$15="margine",MAX(0,AN24-(AK24-AL24-AM24)),0) | AO25: =IF(Ipotesi!$B$15="margine",MIN(AK25,AL25+AM25+AN25+0.5*MAX(0,(AK25-AL25-AM25)-AN25)),AI25*'Conti per prodotto'!$I$10) | AP25: =AO25-AL25-AM25 | AQ25: =AQ24+AP25 | AR25: =AK25-AO25 | AS25: =AS24+AR25 | AT25: =IF(IF(Ipotesi!$B$15="margine",(AK25-AL25-AM25)/2,AP25)>=Ipotesi!$B$14,AG25,"") | AU25: =IF(AND(AG25>1,AQ25>=0),AG25,"")
A26: 9 | B26: 1 | C26: =ROUND(B$3*MIN(1,9/B$6)*Stagionalità!$B$12,0) | D26: =C26*'Conti per prodotto'!$B$10 | E26: =C26*('Conti per prodotto'!$O$10+'Conti per prodotto'!$I$10) | F26: ='Costi B2Brand'!$C$6 | G26: =B$7 | H26: =IF(Ipotesi!$B$15="margine",MAX(0,H25-(E25-F25-G25)),0) | I26: =IF(Ipotesi!$B$15="margine",MIN(E26,F26+G26+H26+0.5*MAX(0,(E26-F26-G26)-H26)),C26*'Conti per prodotto'!$I$10) | J26: =I26-F26-G26 | K26: =K25+J26 | L26: =E26-I26 | M26: =M25+L26 | N26: =IF(IF(Ipotesi!$B$15="margine",(E26-F26-G26)/2,J26)>=Ipotesi!$B$14,A26,"") | O26: =IF(AND(A26>1,K26>=0),A26,"") | Q26: 9 | R26: 1 | S26: =ROUND(C$3*MIN(1,9/C$6)*Stagionalità!$B$12,0) | T26: =S26*'Conti per prodotto'!$B$10 | U26: =S26*('Conti per prodotto'!$O$10+'Conti per prodotto'!$I$10) | V26: ='Costi B2Brand'!$C$6 | W26: =C$7 | X26: =IF(Ipotesi!$B$15="margine",MAX(0,X25-(U25-V25-W25)),0) | Y26: =IF(Ipotesi!$B$15="margine",MIN(U26,V26+W26+X26+0.5*MAX(0,(U26-V26-W26)-X26)),S26*'Conti per prodotto'!$I$10) | Z26: =Y26-V26-W26 | AA26: =AA25+Z26 | AB26: =U26-Y26 | AC26: =AC25+AB26 | AD26: =IF(IF(Ipotesi!$B$15="margine",(U26-V26-W26)/2,Z26)>=Ipotesi!$B$14,Q26,"") | AE26: =IF(AND(Q26>1,AA26>=0),Q26,"") | AG26: 9 | AH26: 1 | AI26: =ROUND(D$3*MIN(1,9/D$6)*Stagionalità!$B$12,0) | AJ26: =AI26*'Conti per prodotto'!$B$10 | AK26: =AI26*('Conti per prodotto'!$O$10+'Conti per prodotto'!$I$10) | AL26: ='Costi B2Brand'!$C$6 | AM26: =D$7 | AN26: =IF(Ipotesi!$B$15="margine",MAX(0,AN25-(AK25-AL25-AM25)),0) | AO26: =IF(Ipotesi!$B$15="margine",MIN(AK26,AL26+AM26+AN26+0.5*MAX(0,(AK26-AL26-AM26)-AN26)),AI26*'Conti per prodotto'!$I$10) | AP26: =AO26-AL26-AM26 | AQ26: =AQ25+AP26 | AR26: =AK26-AO26 | AS26: =AS25+AR26 | AT26: =IF(IF(Ipotesi!$B$15="margine",(AK26-AL26-AM26)/2,AP26)>=Ipotesi!$B$14,AG26,"") | AU26: =IF(AND(AG26>1,AQ26>=0),AG26,"")
A27: 10 | B27: 1 | C27: =ROUND(B$3*MIN(1,10/B$6)*Stagionalità!$B$13,0) | D27: =C27*'Conti per prodotto'!$B$10 | E27: =C27*('Conti per prodotto'!$O$10+'Conti per prodotto'!$I$10) | F27: ='Costi B2Brand'!$C$6 | G27: =B$7 | H27: =IF(Ipotesi!$B$15="margine",MAX(0,H26-(E26-F26-G26)),0) | I27: =IF(Ipotesi!$B$15="margine",MIN(E27,F27+G27+H27+0.5*MAX(0,(E27-F27-G27)-H27)),C27*'Conti per prodotto'!$I$10) | J27: =I27-F27-G27 | K27: =K26+J27 | L27: =E27-I27 | M27: =M26+L27 | N27: =IF(IF(Ipotesi!$B$15="margine",(E27-F27-G27)/2,J27)>=Ipotesi!$B$14,A27,"") | O27: =IF(AND(A27>1,K27>=0),A27,"") | Q27: 10 | R27: 1 | S27: =ROUND(C$3*MIN(1,10/C$6)*Stagionalità!$B$13,0) | T27: =S27*'Conti per prodotto'!$B$10 | U27: =S27*('Conti per prodotto'!$O$10+'Conti per prodotto'!$I$10) | V27: ='Costi B2Brand'!$C$6 | W27: =C$7 | X27: =IF(Ipotesi!$B$15="margine",MAX(0,X26-(U26-V26-W26)),0) | Y27: =IF(Ipotesi!$B$15="margine",MIN(U27,V27+W27+X27+0.5*MAX(0,(U27-V27-W27)-X27)),S27*'Conti per prodotto'!$I$10) | Z27: =Y27-V27-W27 | AA27: =AA26+Z27 | AB27: =U27-Y27 | AC27: =AC26+AB27 | AD27: =IF(IF(Ipotesi!$B$15="margine",(U27-V27-W27)/2,Z27)>=Ipotesi!$B$14,Q27,"") | AE27: =IF(AND(Q27>1,AA27>=0),Q27,"") | AG27: 10 | AH27: 1 | AI27: =ROUND(D$3*MIN(1,10/D$6)*Stagionalità!$B$13,0) | AJ27: =AI27*'Conti per prodotto'!$B$10 | AK27: =AI27*('Conti per prodotto'!$O$10+'Conti per prodotto'!$I$10) | AL27: ='Costi B2Brand'!$C$6 | AM27: =D$7 | AN27: =IF(Ipotesi!$B$15="margine",MAX(0,AN26-(AK26-AL26-AM26)),0) | AO27: =IF(Ipotesi!$B$15="margine",MIN(AK27,AL27+AM27+AN27+0.5*MAX(0,(AK27-AL27-AM27)-AN27)),AI27*'Conti per prodotto'!$I$10) | AP27: =AO27-AL27-AM27 | AQ27: =AQ26+AP27 | AR27: =AK27-AO27 | AS27: =AS26+AR27 | AT27: =IF(IF(Ipotesi!$B$15="margine",(AK27-AL27-AM27)/2,AP27)>=Ipotesi!$B$14,AG27,"") | AU27: =IF(AND(AG27>1,AQ27>=0),AG27,"")
A28: 11 | B28: 1 | C28: =ROUND(B$3*MIN(1,11/B$6)*Stagionalità!$B$2,0) | D28: =C28*'Conti per prodotto'!$B$10 | E28: =C28*('Conti per prodotto'!$O$10+'Conti per prodotto'!$I$10) | F28: ='Costi B2Brand'!$C$6 | G28: =B$7 | H28: =IF(Ipotesi!$B$15="margine",MAX(0,H27-(E27-F27-G27)),0) | I28: =IF(Ipotesi!$B$15="margine",MIN(E28,F28+G28+H28+0.5*MAX(0,(E28-F28-G28)-H28)),C28*'Conti per prodotto'!$I$10) | J28: =I28-F28-G28 | K28: =K27+J28 | L28: =E28-I28 | M28: =M27+L28 | N28: =IF(IF(Ipotesi!$B$15="margine",(E28-F28-G28)/2,J28)>=Ipotesi!$B$14,A28,"") | O28: =IF(AND(A28>1,K28>=0),A28,"") | Q28: 11 | R28: 1 | S28: =ROUND(C$3*MIN(1,11/C$6)*Stagionalità!$B$2,0) | T28: =S28*'Conti per prodotto'!$B$10 | U28: =S28*('Conti per prodotto'!$O$10+'Conti per prodotto'!$I$10) | V28: ='Costi B2Brand'!$C$6 | W28: =C$7 | X28: =IF(Ipotesi!$B$15="margine",MAX(0,X27-(U27-V27-W27)),0) | Y28: =IF(Ipotesi!$B$15="margine",MIN(U28,V28+W28+X28+0.5*MAX(0,(U28-V28-W28)-X28)),S28*'Conti per prodotto'!$I$10) | Z28: =Y28-V28-W28 | AA28: =AA27+Z28 | AB28: =U28-Y28 | AC28: =AC27+AB28 | AD28: =IF(IF(Ipotesi!$B$15="margine",(U28-V28-W28)/2,Z28)>=Ipotesi!$B$14,Q28,"") | AE28: =IF(AND(Q28>1,AA28>=0),Q28,"") | AG28: 11 | AH28: 1 | AI28: =ROUND(D$3*MIN(1,11/D$6)*Stagionalità!$B$2,0) | AJ28: =AI28*'Conti per prodotto'!$B$10 | AK28: =AI28*('Conti per prodotto'!$O$10+'Conti per prodotto'!$I$10) | AL28: ='Costi B2Brand'!$C$6 | AM28: =D$7 | AN28: =IF(Ipotesi!$B$15="margine",MAX(0,AN27-(AK27-AL27-AM27)),0) | AO28: =IF(Ipotesi!$B$15="margine",MIN(AK28,AL28+AM28+AN28+0.5*MAX(0,(AK28-AL28-AM28)-AN28)),AI28*'Conti per prodotto'!$I$10) | AP28: =AO28-AL28-AM28 | AQ28: =AQ27+AP28 | AR28: =AK28-AO28 | AS28: =AS27+AR28 | AT28: =IF(IF(Ipotesi!$B$15="margine",(AK28-AL28-AM28)/2,AP28)>=Ipotesi!$B$14,AG28,"") | AU28: =IF(AND(AG28>1,AQ28>=0),AG28,"")
A29: 12 | B29: 1 | C29: =ROUND(B$3*MIN(1,12/B$6)*Stagionalità!$B$3,0) | D29: =C29*'Conti per prodotto'!$B$10 | E29: =C29*('Conti per prodotto'!$O$10+'Conti per prodotto'!$I$10) | F29: ='Costi B2Brand'!$C$6 | G29: =B$7 | H29: =IF(Ipotesi!$B$15="margine",MAX(0,H28-(E28-F28-G28)),0) | I29: =IF(Ipotesi!$B$15="margine",MIN(E29,F29+G29+H29+0.5*MAX(0,(E29-F29-G29)-H29)),C29*'Conti per prodotto'!$I$10) | J29: =I29-F29-G29 | K29: =K28+J29 | L29: =E29-I29 | M29: =M28+L29 | N29: =IF(IF(Ipotesi!$B$15="margine",(E29-F29-G29)/2,J29)>=Ipotesi!$B$14,A29,"") | O29: =IF(AND(A29>1,K29>=0),A29,"") | Q29: 12 | R29: 1 | S29: =ROUND(C$3*MIN(1,12/C$6)*Stagionalità!$B$3,0) | T29: =S29*'Conti per prodotto'!$B$10 | U29: =S29*('Conti per prodotto'!$O$10+'Conti per prodotto'!$I$10) | V29: ='Costi B2Brand'!$C$6 | W29: =C$7 | X29: =IF(Ipotesi!$B$15="margine",MAX(0,X28-(U28-V28-W28)),0) | Y29: =IF(Ipotesi!$B$15="margine",MIN(U29,V29+W29+X29+0.5*MAX(0,(U29-V29-W29)-X29)),S29*'Conti per prodotto'!$I$10) | Z29: =Y29-V29-W29 | AA29: =AA28+Z29 | AB29: =U29-Y29 | AC29: =AC28+AB29 | AD29: =IF(IF(Ipotesi!$B$15="margine",(U29-V29-W29)/2,Z29)>=Ipotesi!$B$14,Q29,"") | AE29: =IF(AND(Q29>1,AA29>=0),Q29,"") | AG29: 12 | AH29: 1 | AI29: =ROUND(D$3*MIN(1,12/D$6)*Stagionalità!$B$3,0) | AJ29: =AI29*'Conti per prodotto'!$B$10 | AK29: =AI29*('Conti per prodotto'!$O$10+'Conti per prodotto'!$I$10) | AL29: ='Costi B2Brand'!$C$6 | AM29: =D$7 | AN29: =IF(Ipotesi!$B$15="margine",MAX(0,AN28-(AK28-AL28-AM28)),0) | AO29: =IF(Ipotesi!$B$15="margine",MIN(AK29,AL29+AM29+AN29+0.5*MAX(0,(AK29-AL29-AM29)-AN29)),AI29*'Conti per prodotto'!$I$10) | AP29: =AO29-AL29-AM29 | AQ29: =AQ28+AP29 | AR29: =AK29-AO29 | AS29: =AS28+AR29 | AT29: =IF(IF(Ipotesi!$B$15="margine",(AK29-AL29-AM29)/2,AP29)>=Ipotesi!$B$14,AG29,"") | AU29: =IF(AND(AG29>1,AQ29>=0),AG29,"")
A30: 13 | B30: 2 | C30: =ROUND((B$3+(B$13-B$3)*1/12)*Stagionalità!$B$4,0) | D30: =C30*'Conti per prodotto'!$B$10 | E30: =C30*('Conti per prodotto'!$O$10+'Conti per prodotto'!$I$10) | F30: ='Costi B2Brand'!$D$6 | G30: =B$8 | H30: =IF(Ipotesi!$B$15="margine",MAX(0,H29-(E29-F29-G29)),0) | I30: =IF(Ipotesi!$B$15="margine",MIN(E30,F30+G30+H30+0.5*MAX(0,(E30-F30-G30)-H30)),C30*'Conti per prodotto'!$I$10) | J30: =I30-F30-G30 | K30: =K29+J30 | L30: =E30-I30 | M30: =M29+L30 | N30: =IF(IF(Ipotesi!$B$15="margine",(E30-F30-G30)/2,J30)>=Ipotesi!$B$14,A30,"") | O30: =IF(AND(A30>1,K30>=0),A30,"") | Q30: 13 | R30: 2 | S30: =ROUND((C$3+(C$13-C$3)*1/12)*Stagionalità!$B$4,0) | T30: =S30*'Conti per prodotto'!$B$10 | U30: =S30*('Conti per prodotto'!$O$10+'Conti per prodotto'!$I$10) | V30: ='Costi B2Brand'!$D$6 | W30: =C$8 | X30: =IF(Ipotesi!$B$15="margine",MAX(0,X29-(U29-V29-W29)),0) | Y30: =IF(Ipotesi!$B$15="margine",MIN(U30,V30+W30+X30+0.5*MAX(0,(U30-V30-W30)-X30)),S30*'Conti per prodotto'!$I$10) | Z30: =Y30-V30-W30 | AA30: =AA29+Z30 | AB30: =U30-Y30 | AC30: =AC29+AB30 | AD30: =IF(IF(Ipotesi!$B$15="margine",(U30-V30-W30)/2,Z30)>=Ipotesi!$B$14,Q30,"") | AE30: =IF(AND(Q30>1,AA30>=0),Q30,"") | AG30: 13 | AH30: 2 | AI30: =ROUND((D$3+(D$13-D$3)*1/12)*Stagionalità!$B$4,0) | AJ30: =AI30*'Conti per prodotto'!$B$10 | AK30: =AI30*('Conti per prodotto'!$O$10+'Conti per prodotto'!$I$10) | AL30: ='Costi B2Brand'!$D$6 | AM30: =D$8 | AN30: =IF(Ipotesi!$B$15="margine",MAX(0,AN29-(AK29-AL29-AM29)),0) | AO30: =IF(Ipotesi!$B$15="margine",MIN(AK30,AL30+AM30+AN30+0.5*MAX(0,(AK30-AL30-AM30)-AN30)),AI30*'Conti per prodotto'!$I$10) | AP30: =AO30-AL30-AM30 | AQ30: =AQ29+AP30 | AR30: =AK30-AO30 | AS30: =AS29+AR30 | AT30: =IF(IF(Ipotesi!$B$15="margine",(AK30-AL30-AM30)/2,AP30)>=Ipotesi!$B$14,AG30,"") | AU30: =IF(AND(AG30>1,AQ30>=0),AG30,"")
A31: 14 | B31: 2 | C31: =ROUND((B$3+(B$13-B$3)*2/12)*Stagionalità!$B$5,0) | D31: =C31*'Conti per prodotto'!$B$10 | E31: =C31*('Conti per prodotto'!$O$10+'Conti per prodotto'!$I$10) | F31: ='Costi B2Brand'!$D$6 | G31: =B$8 | H31: =IF(Ipotesi!$B$15="margine",MAX(0,H30-(E30-F30-G30)),0) | I31: =IF(Ipotesi!$B$15="margine",MIN(E31,F31+G31+H31+0.5*MAX(0,(E31-F31-G31)-H31)),C31*'Conti per prodotto'!$I$10) | J31: =I31-F31-G31 | K31: =K30+J31 | L31: =E31-I31 | M31: =M30+L31 | N31: =IF(IF(Ipotesi!$B$15="margine",(E31-F31-G31)/2,J31)>=Ipotesi!$B$14,A31,"") | O31: =IF(AND(A31>1,K31>=0),A31,"") | Q31: 14 | R31: 2 | S31: =ROUND((C$3+(C$13-C$3)*2/12)*Stagionalità!$B$5,0) | T31: =S31*'Conti per prodotto'!$B$10 | U31: =S31*('Conti per prodotto'!$O$10+'Conti per prodotto'!$I$10) | V31: ='Costi B2Brand'!$D$6 | W31: =C$8 | X31: =IF(Ipotesi!$B$15="margine",MAX(0,X30-(U30-V30-W30)),0) | Y31: =IF(Ipotesi!$B$15="margine",MIN(U31,V31+W31+X31+0.5*MAX(0,(U31-V31-W31)-X31)),S31*'Conti per prodotto'!$I$10) | Z31: =Y31-V31-W31 | AA31: =AA30+Z31 | AB31: =U31-Y31 | AC31: =AC30+AB31 | AD31: =IF(IF(Ipotesi!$B$15="margine",(U31-V31-W31)/2,Z31)>=Ipotesi!$B$14,Q31,"") | AE31: =IF(AND(Q31>1,AA31>=0),Q31,"") | AG31: 14 | AH31: 2 | AI31: =ROUND((D$3+(D$13-D$3)*2/12)*Stagionalità!$B$5,0) | AJ31: =AI31*'Conti per prodotto'!$B$10 | AK31: =AI31*('Conti per prodotto'!$O$10+'Conti per prodotto'!$I$10) | AL31: ='Costi B2Brand'!$D$6 | AM31: =D$8 | AN31: =IF(Ipotesi!$B$15="margine",MAX(0,AN30-(AK30-AL30-AM30)),0) | AO31: =IF(Ipotesi!$B$15="margine",MIN(AK31,AL31+AM31+AN31+0.5*MAX(0,(AK31-AL31-AM31)-AN31)),AI31*'Conti per prodotto'!$I$10) | AP31: =AO31-AL31-AM31 | AQ31: =AQ30+AP31 | AR31: =AK31-AO31 | AS31: =AS30+AR31 | AT31: =IF(IF(Ipotesi!$B$15="margine",(AK31-AL31-AM31)/2,AP31)>=Ipotesi!$B$14,AG31,"") | AU31: =IF(AND(AG31>1,AQ31>=0),AG31,"")
A32: 15 | B32: 2 | C32: =ROUND((B$3+(B$13-B$3)*3/12)*Stagionalità!$B$6,0) | D32: =C32*'Conti per prodotto'!$B$10 | E32: =C32*('Conti per prodotto'!$O$10+'Conti per prodotto'!$I$10) | F32: ='Costi B2Brand'!$D$6 | G32: =B$8 | H32: =IF(Ipotesi!$B$15="margine",MAX(0,H31-(E31-F31-G31)),0) | I32: =IF(Ipotesi!$B$15="margine",MIN(E32,F32+G32+H32+0.5*MAX(0,(E32-F32-G32)-H32)),C32*'Conti per prodotto'!$I$10) | J32: =I32-F32-G32 | K32: =K31+J32 | L32: =E32-I32 | M32: =M31+L32 | N32: =IF(IF(Ipotesi!$B$15="margine",(E32-F32-G32)/2,J32)>=Ipotesi!$B$14,A32,"") | O32: =IF(AND(A32>1,K32>=0),A32,"") | Q32: 15 | R32: 2 | S32: =ROUND((C$3+(C$13-C$3)*3/12)*Stagionalità!$B$6,0) | T32: =S32*'Conti per prodotto'!$B$10 | U32: =S32*('Conti per prodotto'!$O$10+'Conti per prodotto'!$I$10) | V32: ='Costi B2Brand'!$D$6 | W32: =C$8 | X32: =IF(Ipotesi!$B$15="margine",MAX(0,X31-(U31-V31-W31)),0) | Y32: =IF(Ipotesi!$B$15="margine",MIN(U32,V32+W32+X32+0.5*MAX(0,(U32-V32-W32)-X32)),S32*'Conti per prodotto'!$I$10) | Z32: =Y32-V32-W32 | AA32: =AA31+Z32 | AB32: =U32-Y32 | AC32: =AC31+AB32 | AD32: =IF(IF(Ipotesi!$B$15="margine",(U32-V32-W32)/2,Z32)>=Ipotesi!$B$14,Q32,"") | AE32: =IF(AND(Q32>1,AA32>=0),Q32,"") | AG32: 15 | AH32: 2 | AI32: =ROUND((D$3+(D$13-D$3)*3/12)*Stagionalità!$B$6,0) | AJ32: =AI32*'Conti per prodotto'!$B$10 | AK32: =AI32*('Conti per prodotto'!$O$10+'Conti per prodotto'!$I$10) | AL32: ='Costi B2Brand'!$D$6 | AM32: =D$8 | AN32: =IF(Ipotesi!$B$15="margine",MAX(0,AN31-(AK31-AL31-AM31)),0) | AO32: =IF(Ipotesi!$B$15="margine",MIN(AK32,AL32+AM32+AN32+0.5*MAX(0,(AK32-AL32-AM32)-AN32)),AI32*'Conti per prodotto'!$I$10) | AP32: =AO32-AL32-AM32 | AQ32: =AQ31+AP32 | AR32: =AK32-AO32 | AS32: =AS31+AR32 | AT32: =IF(IF(Ipotesi!$B$15="margine",(AK32-AL32-AM32)/2,AP32)>=Ipotesi!$B$14,AG32,"") | AU32: =IF(AND(AG32>1,AQ32>=0),AG32,"")
A33: 16 | B33: 2 | C33: =ROUND((B$3+(B$13-B$3)*4/12)*Stagionalità!$B$7,0) | D33: =C33*'Conti per prodotto'!$B$10 | E33: =C33*('Conti per prodotto'!$O$10+'Conti per prodotto'!$I$10) | F33: ='Costi B2Brand'!$D$6 | G33: =B$8 | H33: =IF(Ipotesi!$B$15="margine",MAX(0,H32-(E32-F32-G32)),0) | I33: =IF(Ipotesi!$B$15="margine",MIN(E33,F33+G33+H33+0.5*MAX(0,(E33-F33-G33)-H33)),C33*'Conti per prodotto'!$I$10) | J33: =I33-F33-G33 | K33: =K32+J33 | L33: =E33-I33 | M33: =M32+L33 | N33: =IF(IF(Ipotesi!$B$15="margine",(E33-F33-G33)/2,J33)>=Ipotesi!$B$14,A33,"") | O33: =IF(AND(A33>1,K33>=0),A33,"") | Q33: 16 | R33: 2 | S33: =ROUND((C$3+(C$13-C$3)*4/12)*Stagionalità!$B$7,0) | T33: =S33*'Conti per prodotto'!$B$10 | U33: =S33*('Conti per prodotto'!$O$10+'Conti per prodotto'!$I$10) | V33: ='Costi B2Brand'!$D$6 | W33: =C$8 | X33: =IF(Ipotesi!$B$15="margine",MAX(0,X32-(U32-V32-W32)),0) | Y33: =IF(Ipotesi!$B$15="margine",MIN(U33,V33+W33+X33+0.5*MAX(0,(U33-V33-W33)-X33)),S33*'Conti per prodotto'!$I$10) | Z33: =Y33-V33-W33 | AA33: =AA32+Z33 | AB33: =U33-Y33 | AC33: =AC32+AB33 | AD33: =IF(IF(Ipotesi!$B$15="margine",(U33-V33-W33)/2,Z33)>=Ipotesi!$B$14,Q33,"") | AE33: =IF(AND(Q33>1,AA33>=0),Q33,"") | AG33: 16 | AH33: 2 | AI33: =ROUND((D$3+(D$13-D$3)*4/12)*Stagionalità!$B$7,0) | AJ33: =AI33*'Conti per prodotto'!$B$10 | AK33: =AI33*('Conti per prodotto'!$O$10+'Conti per prodotto'!$I$10) | AL33: ='Costi B2Brand'!$D$6 | AM33: =D$8 | AN33: =IF(Ipotesi!$B$15="margine",MAX(0,AN32-(AK32-AL32-AM32)),0) | AO33: =IF(Ipotesi!$B$15="margine",MIN(AK33,AL33+AM33+AN33+0.5*MAX(0,(AK33-AL33-AM33)-AN33)),AI33*'Conti per prodotto'!$I$10) | AP33: =AO33-AL33-AM33 | AQ33: =AQ32+AP33 | AR33: =AK33-AO33 | AS33: =AS32+AR33 | AT33: =IF(IF(Ipotesi!$B$15="margine",(AK33-AL33-AM33)/2,AP33)>=Ipotesi!$B$14,AG33,"") | AU33: =IF(AND(AG33>1,AQ33>=0),AG33,"")
A34: 17 | B34: 2 | C34: =ROUND((B$3+(B$13-B$3)*5/12)*Stagionalità!$B$8,0) | D34: =C34*'Conti per prodotto'!$B$10 | E34: =C34*('Conti per prodotto'!$O$10+'Conti per prodotto'!$I$10) | F34: ='Costi B2Brand'!$D$6 | G34: =B$8 | H34: =IF(Ipotesi!$B$15="margine",MAX(0,H33-(E33-F33-G33)),0) | I34: =IF(Ipotesi!$B$15="margine",MIN(E34,F34+G34+H34+0.5*MAX(0,(E34-F34-G34)-H34)),C34*'Conti per prodotto'!$I$10) | J34: =I34-F34-G34 | K34: =K33+J34 | L34: =E34-I34 | M34: =M33+L34 | N34: =IF(IF(Ipotesi!$B$15="margine",(E34-F34-G34)/2,J34)>=Ipotesi!$B$14,A34,"") | O34: =IF(AND(A34>1,K34>=0),A34,"") | Q34: 17 | R34: 2 | S34: =ROUND((C$3+(C$13-C$3)*5/12)*Stagionalità!$B$8,0) | T34: =S34*'Conti per prodotto'!$B$10 | U34: =S34*('Conti per prodotto'!$O$10+'Conti per prodotto'!$I$10) | V34: ='Costi B2Brand'!$D$6 | W34: =C$8 | X34: =IF(Ipotesi!$B$15="margine",MAX(0,X33-(U33-V33-W33)),0) | Y34: =IF(Ipotesi!$B$15="margine",MIN(U34,V34+W34+X34+0.5*MAX(0,(U34-V34-W34)-X34)),S34*'Conti per prodotto'!$I$10) | Z34: =Y34-V34-W34 | AA34: =AA33+Z34 | AB34: =U34-Y34 | AC34: =AC33+AB34 | AD34: =IF(IF(Ipotesi!$B$15="margine",(U34-V34-W34)/2,Z34)>=Ipotesi!$B$14,Q34,"") | AE34: =IF(AND(Q34>1,AA34>=0),Q34,"") | AG34: 17 | AH34: 2 | AI34: =ROUND((D$3+(D$13-D$3)*5/12)*Stagionalità!$B$8,0) | AJ34: =AI34*'Conti per prodotto'!$B$10 | AK34: =AI34*('Conti per prodotto'!$O$10+'Conti per prodotto'!$I$10) | AL34: ='Costi B2Brand'!$D$6 | AM34: =D$8 | AN34: =IF(Ipotesi!$B$15="margine",MAX(0,AN33-(AK33-AL33-AM33)),0) | AO34: =IF(Ipotesi!$B$15="margine",MIN(AK34,AL34+AM34+AN34+0.5*MAX(0,(AK34-AL34-AM34)-AN34)),AI34*'Conti per prodotto'!$I$10) | AP34: =AO34-AL34-AM34 | AQ34: =AQ33+AP34 | AR34: =AK34-AO34 | AS34: =AS33+AR34 | AT34: =IF(IF(Ipotesi!$B$15="margine",(AK34-AL34-AM34)/2,AP34)>=Ipotesi!$B$14,AG34,"") | AU34: =IF(AND(AG34>1,AQ34>=0),AG34,"")
A35: 18 | B35: 2 | C35: =ROUND((B$3+(B$13-B$3)*6/12)*Stagionalità!$B$9,0) | D35: =C35*'Conti per prodotto'!$B$10 | E35: =C35*('Conti per prodotto'!$O$10+'Conti per prodotto'!$I$10) | F35: ='Costi B2Brand'!$D$6 | G35: =B$8 | H35: =IF(Ipotesi!$B$15="margine",MAX(0,H34-(E34-F34-G34)),0) | I35: =IF(Ipotesi!$B$15="margine",MIN(E35,F35+G35+H35+0.5*MAX(0,(E35-F35-G35)-H35)),C35*'Conti per prodotto'!$I$10) | J35: =I35-F35-G35 | K35: =K34+J35 | L35: =E35-I35 | M35: =M34+L35 | N35: =IF(IF(Ipotesi!$B$15="margine",(E35-F35-G35)/2,J35)>=Ipotesi!$B$14,A35,"") | O35: =IF(AND(A35>1,K35>=0),A35,"") | Q35: 18 | R35: 2 | S35: =ROUND((C$3+(C$13-C$3)*6/12)*Stagionalità!$B$9,0) | T35: =S35*'Conti per prodotto'!$B$10 | U35: =S35*('Conti per prodotto'!$O$10+'Conti per prodotto'!$I$10) | V35: ='Costi B2Brand'!$D$6 | W35: =C$8 | X35: =IF(Ipotesi!$B$15="margine",MAX(0,X34-(U34-V34-W34)),0) | Y35: =IF(Ipotesi!$B$15="margine",MIN(U35,V35+W35+X35+0.5*MAX(0,(U35-V35-W35)-X35)),S35*'Conti per prodotto'!$I$10) | Z35: =Y35-V35-W35 | AA35: =AA34+Z35 | AB35: =U35-Y35 | AC35: =AC34+AB35 | AD35: =IF(IF(Ipotesi!$B$15="margine",(U35-V35-W35)/2,Z35)>=Ipotesi!$B$14,Q35,"") | AE35: =IF(AND(Q35>1,AA35>=0),Q35,"") | AG35: 18 | AH35: 2 | AI35: =ROUND((D$3+(D$13-D$3)*6/12)*Stagionalità!$B$9,0) | AJ35: =AI35*'Conti per prodotto'!$B$10 | AK35: =AI35*('Conti per prodotto'!$O$10+'Conti per prodotto'!$I$10) | AL35: ='Costi B2Brand'!$D$6 | AM35: =D$8 | AN35: =IF(Ipotesi!$B$15="margine",MAX(0,AN34-(AK34-AL34-AM34)),0) | AO35: =IF(Ipotesi!$B$15="margine",MIN(AK35,AL35+AM35+AN35+0.5*MAX(0,(AK35-AL35-AM35)-AN35)),AI35*'Conti per prodotto'!$I$10) | AP35: =AO35-AL35-AM35 | AQ35: =AQ34+AP35 | AR35: =AK35-AO35 | AS35: =AS34+AR35 | AT35: =IF(IF(Ipotesi!$B$15="margine",(AK35-AL35-AM35)/2,AP35)>=Ipotesi!$B$14,AG35,"") | AU35: =IF(AND(AG35>1,AQ35>=0),AG35,"")
A36: 19 | B36: 2 | C36: =ROUND((B$3+(B$13-B$3)*7/12)*Stagionalità!$B$10,0) | D36: =C36*'Conti per prodotto'!$B$10 | E36: =C36*('Conti per prodotto'!$O$10+'Conti per prodotto'!$I$10) | F36: ='Costi B2Brand'!$D$6 | G36: =B$8 | H36: =IF(Ipotesi!$B$15="margine",MAX(0,H35-(E35-F35-G35)),0) | I36: =IF(Ipotesi!$B$15="margine",MIN(E36,F36+G36+H36+0.5*MAX(0,(E36-F36-G36)-H36)),C36*'Conti per prodotto'!$I$10) | J36: =I36-F36-G36 | K36: =K35+J36 | L36: =E36-I36 | M36: =M35+L36 | N36: =IF(IF(Ipotesi!$B$15="margine",(E36-F36-G36)/2,J36)>=Ipotesi!$B$14,A36,"") | O36: =IF(AND(A36>1,K36>=0),A36,"") | Q36: 19 | R36: 2 | S36: =ROUND((C$3+(C$13-C$3)*7/12)*Stagionalità!$B$10,0) | T36: =S36*'Conti per prodotto'!$B$10 | U36: =S36*('Conti per prodotto'!$O$10+'Conti per prodotto'!$I$10) | V36: ='Costi B2Brand'!$D$6 | W36: =C$8 | X36: =IF(Ipotesi!$B$15="margine",MAX(0,X35-(U35-V35-W35)),0) | Y36: =IF(Ipotesi!$B$15="margine",MIN(U36,V36+W36+X36+0.5*MAX(0,(U36-V36-W36)-X36)),S36*'Conti per prodotto'!$I$10) | Z36: =Y36-V36-W36 | AA36: =AA35+Z36 | AB36: =U36-Y36 | AC36: =AC35+AB36 | AD36: =IF(IF(Ipotesi!$B$15="margine",(U36-V36-W36)/2,Z36)>=Ipotesi!$B$14,Q36,"") | AE36: =IF(AND(Q36>1,AA36>=0),Q36,"") | AG36: 19 | AH36: 2 | AI36: =ROUND((D$3+(D$13-D$3)*7/12)*Stagionalità!$B$10,0) | AJ36: =AI36*'Conti per prodotto'!$B$10 | AK36: =AI36*('Conti per prodotto'!$O$10+'Conti per prodotto'!$I$10) | AL36: ='Costi B2Brand'!$D$6 | AM36: =D$8 | AN36: =IF(Ipotesi!$B$15="margine",MAX(0,AN35-(AK35-AL35-AM35)),0) | AO36: =IF(Ipotesi!$B$15="margine",MIN(AK36,AL36+AM36+AN36+0.5*MAX(0,(AK36-AL36-AM36)-AN36)),AI36*'Conti per prodotto'!$I$10) | AP36: =AO36-AL36-AM36 | AQ36: =AQ35+AP36 | AR36: =AK36-AO36 | AS36: =AS35+AR36 | AT36: =IF(IF(Ipotesi!$B$15="margine",(AK36-AL36-AM36)/2,AP36)>=Ipotesi!$B$14,AG36,"") | AU36: =IF(AND(AG36>1,AQ36>=0),AG36,"")
A37: 20 | B37: 2 | C37: =ROUND((B$3+(B$13-B$3)*8/12)*Stagionalità!$B$11,0) | D37: =C37*'Conti per prodotto'!$B$10 | E37: =C37*('Conti per prodotto'!$O$10+'Conti per prodotto'!$I$10) | F37: ='Costi B2Brand'!$D$6 | G37: =B$8 | H37: =IF(Ipotesi!$B$15="margine",MAX(0,H36-(E36-F36-G36)),0) | I37: =IF(Ipotesi!$B$15="margine",MIN(E37,F37+G37+H37+0.5*MAX(0,(E37-F37-G37)-H37)),C37*'Conti per prodotto'!$I$10) | J37: =I37-F37-G37 | K37: =K36+J37 | L37: =E37-I37 | M37: =M36+L37 | N37: =IF(IF(Ipotesi!$B$15="margine",(E37-F37-G37)/2,J37)>=Ipotesi!$B$14,A37,"") | O37: =IF(AND(A37>1,K37>=0),A37,"") | Q37: 20 | R37: 2 | S37: =ROUND((C$3+(C$13-C$3)*8/12)*Stagionalità!$B$11,0) | T37: =S37*'Conti per prodotto'!$B$10 | U37: =S37*('Conti per prodotto'!$O$10+'Conti per prodotto'!$I$10) | V37: ='Costi B2Brand'!$D$6 | W37: =C$8 | X37: =IF(Ipotesi!$B$15="margine",MAX(0,X36-(U36-V36-W36)),0) | Y37: =IF(Ipotesi!$B$15="margine",MIN(U37,V37+W37+X37+0.5*MAX(0,(U37-V37-W37)-X37)),S37*'Conti per prodotto'!$I$10) | Z37: =Y37-V37-W37 | AA37: =AA36+Z37 | AB37: =U37-Y37 | AC37: =AC36+AB37 | AD37: =IF(IF(Ipotesi!$B$15="margine",(U37-V37-W37)/2,Z37)>=Ipotesi!$B$14,Q37,"") | AE37: =IF(AND(Q37>1,AA37>=0),Q37,"") | AG37: 20 | AH37: 2 | AI37: =ROUND((D$3+(D$13-D$3)*8/12)*Stagionalità!$B$11,0) | AJ37: =AI37*'Conti per prodotto'!$B$10 | AK37: =AI37*('Conti per prodotto'!$O$10+'Conti per prodotto'!$I$10) | AL37: ='Costi B2Brand'!$D$6 | AM37: =D$8 | AN37: =IF(Ipotesi!$B$15="margine",MAX(0,AN36-(AK36-AL36-AM36)),0) | AO37: =IF(Ipotesi!$B$15="margine",MIN(AK37,AL37+AM37+AN37+0.5*MAX(0,(AK37-AL37-AM37)-AN37)),AI37*'Conti per prodotto'!$I$10) | AP37: =AO37-AL37-AM37 | AQ37: =AQ36+AP37 | AR37: =AK37-AO37 | AS37: =AS36+AR37 | AT37: =IF(IF(Ipotesi!$B$15="margine",(AK37-AL37-AM37)/2,AP37)>=Ipotesi!$B$14,AG37,"") | AU37: =IF(AND(AG37>1,AQ37>=0),AG37,"")
A38: 21 | B38: 2 | C38: =ROUND((B$3+(B$13-B$3)*9/12)*Stagionalità!$B$12,0) | D38: =C38*'Conti per prodotto'!$B$10 | E38: =C38*('Conti per prodotto'!$O$10+'Conti per prodotto'!$I$10) | F38: ='Costi B2Brand'!$D$6 | G38: =B$8 | H38: =IF(Ipotesi!$B$15="margine",MAX(0,H37-(E37-F37-G37)),0) | I38: =IF(Ipotesi!$B$15="margine",MIN(E38,F38+G38+H38+0.5*MAX(0,(E38-F38-G38)-H38)),C38*'Conti per prodotto'!$I$10) | J38: =I38-F38-G38 | K38: =K37+J38 | L38: =E38-I38 | M38: =M37+L38 | N38: =IF(IF(Ipotesi!$B$15="margine",(E38-F38-G38)/2,J38)>=Ipotesi!$B$14,A38,"") | O38: =IF(AND(A38>1,K38>=0),A38,"") | Q38: 21 | R38: 2 | S38: =ROUND((C$3+(C$13-C$3)*9/12)*Stagionalità!$B$12,0) | T38: =S38*'Conti per prodotto'!$B$10 | U38: =S38*('Conti per prodotto'!$O$10+'Conti per prodotto'!$I$10) | V38: ='Costi B2Brand'!$D$6 | W38: =C$8 | X38: =IF(Ipotesi!$B$15="margine",MAX(0,X37-(U37-V37-W37)),0) | Y38: =IF(Ipotesi!$B$15="margine",MIN(U38,V38+W38+X38+0.5*MAX(0,(U38-V38-W38)-X38)),S38*'Conti per prodotto'!$I$10) | Z38: =Y38-V38-W38 | AA38: =AA37+Z38 | AB38: =U38-Y38 | AC38: =AC37+AB38 | AD38: =IF(IF(Ipotesi!$B$15="margine",(U38-V38-W38)/2,Z38)>=Ipotesi!$B$14,Q38,"") | AE38: =IF(AND(Q38>1,AA38>=0),Q38,"") | AG38: 21 | AH38: 2 | AI38: =ROUND((D$3+(D$13-D$3)*9/12)*Stagionalità!$B$12,0) | AJ38: =AI38*'Conti per prodotto'!$B$10 | AK38: =AI38*('Conti per prodotto'!$O$10+'Conti per prodotto'!$I$10) | AL38: ='Costi B2Brand'!$D$6 | AM38: =D$8 | AN38: =IF(Ipotesi!$B$15="margine",MAX(0,AN37-(AK37-AL37-AM37)),0) | AO38: =IF(Ipotesi!$B$15="margine",MIN(AK38,AL38+AM38+AN38+0.5*MAX(0,(AK38-AL38-AM38)-AN38)),AI38*'Conti per prodotto'!$I$10) | AP38: =AO38-AL38-AM38 | AQ38: =AQ37+AP38 | AR38: =AK38-AO38 | AS38: =AS37+AR38 | AT38: =IF(IF(Ipotesi!$B$15="margine",(AK38-AL38-AM38)/2,AP38)>=Ipotesi!$B$14,AG38,"") | AU38: =IF(AND(AG38>1,AQ38>=0),AG38,"")
A39: 22 | B39: 2 | C39: =ROUND((B$3+(B$13-B$3)*10/12)*Stagionalità!$B$13,0) | D39: =C39*'Conti per prodotto'!$B$10 | E39: =C39*('Conti per prodotto'!$O$10+'Conti per prodotto'!$I$10) | F39: ='Costi B2Brand'!$D$6 | G39: =B$8 | H39: =IF(Ipotesi!$B$15="margine",MAX(0,H38-(E38-F38-G38)),0) | I39: =IF(Ipotesi!$B$15="margine",MIN(E39,F39+G39+H39+0.5*MAX(0,(E39-F39-G39)-H39)),C39*'Conti per prodotto'!$I$10) | J39: =I39-F39-G39 | K39: =K38+J39 | L39: =E39-I39 | M39: =M38+L39 | N39: =IF(IF(Ipotesi!$B$15="margine",(E39-F39-G39)/2,J39)>=Ipotesi!$B$14,A39,"") | O39: =IF(AND(A39>1,K39>=0),A39,"") | Q39: 22 | R39: 2 | S39: =ROUND((C$3+(C$13-C$3)*10/12)*Stagionalità!$B$13,0) | T39: =S39*'Conti per prodotto'!$B$10 | U39: =S39*('Conti per prodotto'!$O$10+'Conti per prodotto'!$I$10) | V39: ='Costi B2Brand'!$D$6 | W39: =C$8 | X39: =IF(Ipotesi!$B$15="margine",MAX(0,X38-(U38-V38-W38)),0) | Y39: =IF(Ipotesi!$B$15="margine",MIN(U39,V39+W39+X39+0.5*MAX(0,(U39-V39-W39)-X39)),S39*'Conti per prodotto'!$I$10) | Z39: =Y39-V39-W39 | AA39: =AA38+Z39 | AB39: =U39-Y39 | AC39: =AC38+AB39 | AD39: =IF(IF(Ipotesi!$B$15="margine",(U39-V39-W39)/2,Z39)>=Ipotesi!$B$14,Q39,"") | AE39: =IF(AND(Q39>1,AA39>=0),Q39,"") | AG39: 22 | AH39: 2 | AI39: =ROUND((D$3+(D$13-D$3)*10/12)*Stagionalità!$B$13,0) | AJ39: =AI39*'Conti per prodotto'!$B$10 | AK39: =AI39*('Conti per prodotto'!$O$10+'Conti per prodotto'!$I$10) | AL39: ='Costi B2Brand'!$D$6 | AM39: =D$8 | AN39: =IF(Ipotesi!$B$15="margine",MAX(0,AN38-(AK38-AL38-AM38)),0) | AO39: =IF(Ipotesi!$B$15="margine",MIN(AK39,AL39+AM39+AN39+0.5*MAX(0,(AK39-AL39-AM39)-AN39)),AI39*'Conti per prodotto'!$I$10) | AP39: =AO39-AL39-AM39 | AQ39: =AQ38+AP39 | AR39: =AK39-AO39 | AS39: =AS38+AR39 | AT39: =IF(IF(Ipotesi!$B$15="margine",(AK39-AL39-AM39)/2,AP39)>=Ipotesi!$B$14,AG39,"") | AU39: =IF(AND(AG39>1,AQ39>=0),AG39,"")
A40: 23 | B40: 2 | C40: =ROUND((B$3+(B$13-B$3)*11/12)*Stagionalità!$B$2,0) | D40: =C40*'Conti per prodotto'!$B$10 | E40: =C40*('Conti per prodotto'!$O$10+'Conti per prodotto'!$I$10) | F40: ='Costi B2Brand'!$D$6 | G40: =B$8 | H40: =IF(Ipotesi!$B$15="margine",MAX(0,H39-(E39-F39-G39)),0) | I40: =IF(Ipotesi!$B$15="margine",MIN(E40,F40+G40+H40+0.5*MAX(0,(E40-F40-G40)-H40)),C40*'Conti per prodotto'!$I$10) | J40: =I40-F40-G40 | K40: =K39+J40 | L40: =E40-I40 | M40: =M39+L40 | N40: =IF(IF(Ipotesi!$B$15="margine",(E40-F40-G40)/2,J40)>=Ipotesi!$B$14,A40,"") | O40: =IF(AND(A40>1,K40>=0),A40,"") | Q40: 23 | R40: 2 | S40: =ROUND((C$3+(C$13-C$3)*11/12)*Stagionalità!$B$2,0) | T40: =S40*'Conti per prodotto'!$B$10 | U40: =S40*('Conti per prodotto'!$O$10+'Conti per prodotto'!$I$10) | V40: ='Costi B2Brand'!$D$6 | W40: =C$8 | X40: =IF(Ipotesi!$B$15="margine",MAX(0,X39-(U39-V39-W39)),0) | Y40: =IF(Ipotesi!$B$15="margine",MIN(U40,V40+W40+X40+0.5*MAX(0,(U40-V40-W40)-X40)),S40*'Conti per prodotto'!$I$10) | Z40: =Y40-V40-W40 | AA40: =AA39+Z40 | AB40: =U40-Y40 | AC40: =AC39+AB40 | AD40: =IF(IF(Ipotesi!$B$15="margine",(U40-V40-W40)/2,Z40)>=Ipotesi!$B$14,Q40,"") | AE40: =IF(AND(Q40>1,AA40>=0),Q40,"") | AG40: 23 | AH40: 2 | AI40: =ROUND((D$3+(D$13-D$3)*11/12)*Stagionalità!$B$2,0) | AJ40: =AI40*'Conti per prodotto'!$B$10 | AK40: =AI40*('Conti per prodotto'!$O$10+'Conti per prodotto'!$I$10) | AL40: ='Costi B2Brand'!$D$6 | AM40: =D$8 | AN40: =IF(Ipotesi!$B$15="margine",MAX(0,AN39-(AK39-AL39-AM39)),0) | AO40: =IF(Ipotesi!$B$15="margine",MIN(AK40,AL40+AM40+AN40+0.5*MAX(0,(AK40-AL40-AM40)-AN40)),AI40*'Conti per prodotto'!$I$10) | AP40: =AO40-AL40-AM40 | AQ40: =AQ39+AP40 | AR40: =AK40-AO40 | AS40: =AS39+AR40 | AT40: =IF(IF(Ipotesi!$B$15="margine",(AK40-AL40-AM40)/2,AP40)>=Ipotesi!$B$14,AG40,"") | AU40: =IF(AND(AG40>1,AQ40>=0),AG40,"")
A41: 24 | B41: 2 | C41: =ROUND((B$3+(B$13-B$3)*12/12)*Stagionalità!$B$3,0) | D41: =C41*'Conti per prodotto'!$B$10 | E41: =C41*('Conti per prodotto'!$O$10+'Conti per prodotto'!$I$10) | F41: ='Costi B2Brand'!$D$6 | G41: =B$8 | H41: =IF(Ipotesi!$B$15="margine",MAX(0,H40-(E40-F40-G40)),0) | I41: =IF(Ipotesi!$B$15="margine",MIN(E41,F41+G41+H41+0.5*MAX(0,(E41-F41-G41)-H41)),C41*'Conti per prodotto'!$I$10) | J41: =I41-F41-G41 | K41: =K40+J41 | L41: =E41-I41 | M41: =M40+L41 | N41: =IF(IF(Ipotesi!$B$15="margine",(E41-F41-G41)/2,J41)>=Ipotesi!$B$14,A41,"") | O41: =IF(AND(A41>1,K41>=0),A41,"") | Q41: 24 | R41: 2 | S41: =ROUND((C$3+(C$13-C$3)*12/12)*Stagionalità!$B$3,0) | T41: =S41*'Conti per prodotto'!$B$10 | U41: =S41*('Conti per prodotto'!$O$10+'Conti per prodotto'!$I$10) | V41: ='Costi B2Brand'!$D$6 | W41: =C$8 | X41: =IF(Ipotesi!$B$15="margine",MAX(0,X40-(U40-V40-W40)),0) | Y41: =IF(Ipotesi!$B$15="margine",MIN(U41,V41+W41+X41+0.5*MAX(0,(U41-V41-W41)-X41)),S41*'Conti per prodotto'!$I$10) | Z41: =Y41-V41-W41 | AA41: =AA40+Z41 | AB41: =U41-Y41 | AC41: =AC40+AB41 | AD41: =IF(IF(Ipotesi!$B$15="margine",(U41-V41-W41)/2,Z41)>=Ipotesi!$B$14,Q41,"") | AE41: =IF(AND(Q41>1,AA41>=0),Q41,"") | AG41: 24 | AH41: 2 | AI41: =ROUND((D$3+(D$13-D$3)*12/12)*Stagionalità!$B$3,0) | AJ41: =AI41*'Conti per prodotto'!$B$10 | AK41: =AI41*('Conti per prodotto'!$O$10+'Conti per prodotto'!$I$10) | AL41: ='Costi B2Brand'!$D$6 | AM41: =D$8 | AN41: =IF(Ipotesi!$B$15="margine",MAX(0,AN40-(AK40-AL40-AM40)),0) | AO41: =IF(Ipotesi!$B$15="margine",MIN(AK41,AL41+AM41+AN41+0.5*MAX(0,(AK41-AL41-AM41)-AN41)),AI41*'Conti per prodotto'!$I$10) | AP41: =AO41-AL41-AM41 | AQ41: =AQ40+AP41 | AR41: =AK41-AO41 | AS41: =AS40+AR41 | AT41: =IF(IF(Ipotesi!$B$15="margine",(AK41-AL41-AM41)/2,AP41)>=Ipotesi!$B$14,AG41,"") | AU41: =IF(AND(AG41>1,AQ41>=0),AG41,"")
A42: 25 | B42: 3 | C42: =ROUND((B$13+(B$14-B$13)*1/12)*Stagionalità!$B$4,0) | D42: =C42*'Conti per prodotto'!$B$10 | E42: =C42*('Conti per prodotto'!$O$10+'Conti per prodotto'!$I$10) | F42: ='Costi B2Brand'!$E$6 | G42: =B$9 | H42: =IF(Ipotesi!$B$15="margine",MAX(0,H41-(E41-F41-G41)),0) | I42: =IF(Ipotesi!$B$15="margine",MIN(E42,F42+G42+H42+0.5*MAX(0,(E42-F42-G42)-H42)),C42*'Conti per prodotto'!$I$10) | J42: =I42-F42-G42 | K42: =K41+J42 | L42: =E42-I42 | M42: =M41+L42 | N42: =IF(IF(Ipotesi!$B$15="margine",(E42-F42-G42)/2,J42)>=Ipotesi!$B$14,A42,"") | O42: =IF(AND(A42>1,K42>=0),A42,"") | Q42: 25 | R42: 3 | S42: =ROUND((C$13+(C$14-C$13)*1/12)*Stagionalità!$B$4,0) | T42: =S42*'Conti per prodotto'!$B$10 | U42: =S42*('Conti per prodotto'!$O$10+'Conti per prodotto'!$I$10) | V42: ='Costi B2Brand'!$E$6 | W42: =C$9 | X42: =IF(Ipotesi!$B$15="margine",MAX(0,X41-(U41-V41-W41)),0) | Y42: =IF(Ipotesi!$B$15="margine",MIN(U42,V42+W42+X42+0.5*MAX(0,(U42-V42-W42)-X42)),S42*'Conti per prodotto'!$I$10) | Z42: =Y42-V42-W42 | AA42: =AA41+Z42 | AB42: =U42-Y42 | AC42: =AC41+AB42 | AD42: =IF(IF(Ipotesi!$B$15="margine",(U42-V42-W42)/2,Z42)>=Ipotesi!$B$14,Q42,"") | AE42: =IF(AND(Q42>1,AA42>=0),Q42,"") | AG42: 25 | AH42: 3 | AI42: =ROUND((D$13+(D$14-D$13)*1/12)*Stagionalità!$B$4,0) | AJ42: =AI42*'Conti per prodotto'!$B$10 | AK42: =AI42*('Conti per prodotto'!$O$10+'Conti per prodotto'!$I$10) | AL42: ='Costi B2Brand'!$E$6 | AM42: =D$9 | AN42: =IF(Ipotesi!$B$15="margine",MAX(0,AN41-(AK41-AL41-AM41)),0) | AO42: =IF(Ipotesi!$B$15="margine",MIN(AK42,AL42+AM42+AN42+0.5*MAX(0,(AK42-AL42-AM42)-AN42)),AI42*'Conti per prodotto'!$I$10) | AP42: =AO42-AL42-AM42 | AQ42: =AQ41+AP42 | AR42: =AK42-AO42 | AS42: =AS41+AR42 | AT42: =IF(IF(Ipotesi!$B$15="margine",(AK42-AL42-AM42)/2,AP42)>=Ipotesi!$B$14,AG42,"") | AU42: =IF(AND(AG42>1,AQ42>=0),AG42,"")
A43: 26 | B43: 3 | C43: =ROUND((B$13+(B$14-B$13)*2/12)*Stagionalità!$B$5,0) | D43: =C43*'Conti per prodotto'!$B$10 | E43: =C43*('Conti per prodotto'!$O$10+'Conti per prodotto'!$I$10) | F43: ='Costi B2Brand'!$E$6 | G43: =B$9 | H43: =IF(Ipotesi!$B$15="margine",MAX(0,H42-(E42-F42-G42)),0) | I43: =IF(Ipotesi!$B$15="margine",MIN(E43,F43+G43+H43+0.5*MAX(0,(E43-F43-G43)-H43)),C43*'Conti per prodotto'!$I$10) | J43: =I43-F43-G43 | K43: =K42+J43 | L43: =E43-I43 | M43: =M42+L43 | N43: =IF(IF(Ipotesi!$B$15="margine",(E43-F43-G43)/2,J43)>=Ipotesi!$B$14,A43,"") | O43: =IF(AND(A43>1,K43>=0),A43,"") | Q43: 26 | R43: 3 | S43: =ROUND((C$13+(C$14-C$13)*2/12)*Stagionalità!$B$5,0) | T43: =S43*'Conti per prodotto'!$B$10 | U43: =S43*('Conti per prodotto'!$O$10+'Conti per prodotto'!$I$10) | V43: ='Costi B2Brand'!$E$6 | W43: =C$9 | X43: =IF(Ipotesi!$B$15="margine",MAX(0,X42-(U42-V42-W42)),0) | Y43: =IF(Ipotesi!$B$15="margine",MIN(U43,V43+W43+X43+0.5*MAX(0,(U43-V43-W43)-X43)),S43*'Conti per prodotto'!$I$10) | Z43: =Y43-V43-W43 | AA43: =AA42+Z43 | AB43: =U43-Y43 | AC43: =AC42+AB43 | AD43: =IF(IF(Ipotesi!$B$15="margine",(U43-V43-W43)/2,Z43)>=Ipotesi!$B$14,Q43,"") | AE43: =IF(AND(Q43>1,AA43>=0),Q43,"") | AG43: 26 | AH43: 3 | AI43: =ROUND((D$13+(D$14-D$13)*2/12)*Stagionalità!$B$5,0) | AJ43: =AI43*'Conti per prodotto'!$B$10 | AK43: =AI43*('Conti per prodotto'!$O$10+'Conti per prodotto'!$I$10) | AL43: ='Costi B2Brand'!$E$6 | AM43: =D$9 | AN43: =IF(Ipotesi!$B$15="margine",MAX(0,AN42-(AK42-AL42-AM42)),0) | AO43: =IF(Ipotesi!$B$15="margine",MIN(AK43,AL43+AM43+AN43+0.5*MAX(0,(AK43-AL43-AM43)-AN43)),AI43*'Conti per prodotto'!$I$10) | AP43: =AO43-AL43-AM43 | AQ43: =AQ42+AP43 | AR43: =AK43-AO43 | AS43: =AS42+AR43 | AT43: =IF(IF(Ipotesi!$B$15="margine",(AK43-AL43-AM43)/2,AP43)>=Ipotesi!$B$14,AG43,"") | AU43: =IF(AND(AG43>1,AQ43>=0),AG43,"")
A44: 27 | B44: 3 | C44: =ROUND((B$13+(B$14-B$13)*3/12)*Stagionalità!$B$6,0) | D44: =C44*'Conti per prodotto'!$B$10 | E44: =C44*('Conti per prodotto'!$O$10+'Conti per prodotto'!$I$10) | F44: ='Costi B2Brand'!$E$6 | G44: =B$9 | H44: =IF(Ipotesi!$B$15="margine",MAX(0,H43-(E43-F43-G43)),0) | I44: =IF(Ipotesi!$B$15="margine",MIN(E44,F44+G44+H44+0.5*MAX(0,(E44-F44-G44)-H44)),C44*'Conti per prodotto'!$I$10) | J44: =I44-F44-G44 | K44: =K43+J44 | L44: =E44-I44 | M44: =M43+L44 | N44: =IF(IF(Ipotesi!$B$15="margine",(E44-F44-G44)/2,J44)>=Ipotesi!$B$14,A44,"") | O44: =IF(AND(A44>1,K44>=0),A44,"") | Q44: 27 | R44: 3 | S44: =ROUND((C$13+(C$14-C$13)*3/12)*Stagionalità!$B$6,0) | T44: =S44*'Conti per prodotto'!$B$10 | U44: =S44*('Conti per prodotto'!$O$10+'Conti per prodotto'!$I$10) | V44: ='Costi B2Brand'!$E$6 | W44: =C$9 | X44: =IF(Ipotesi!$B$15="margine",MAX(0,X43-(U43-V43-W43)),0) | Y44: =IF(Ipotesi!$B$15="margine",MIN(U44,V44+W44+X44+0.5*MAX(0,(U44-V44-W44)-X44)),S44*'Conti per prodotto'!$I$10) | Z44: =Y44-V44-W44 | AA44: =AA43+Z44 | AB44: =U44-Y44 | AC44: =AC43+AB44 | AD44: =IF(IF(Ipotesi!$B$15="margine",(U44-V44-W44)/2,Z44)>=Ipotesi!$B$14,Q44,"") | AE44: =IF(AND(Q44>1,AA44>=0),Q44,"") | AG44: 27 | AH44: 3 | AI44: =ROUND((D$13+(D$14-D$13)*3/12)*Stagionalità!$B$6,0) | AJ44: =AI44*'Conti per prodotto'!$B$10 | AK44: =AI44*('Conti per prodotto'!$O$10+'Conti per prodotto'!$I$10) | AL44: ='Costi B2Brand'!$E$6 | AM44: =D$9 | AN44: =IF(Ipotesi!$B$15="margine",MAX(0,AN43-(AK43-AL43-AM43)),0) | AO44: =IF(Ipotesi!$B$15="margine",MIN(AK44,AL44+AM44+AN44+0.5*MAX(0,(AK44-AL44-AM44)-AN44)),AI44*'Conti per prodotto'!$I$10) | AP44: =AO44-AL44-AM44 | AQ44: =AQ43+AP44 | AR44: =AK44-AO44 | AS44: =AS43+AR44 | AT44: =IF(IF(Ipotesi!$B$15="margine",(AK44-AL44-AM44)/2,AP44)>=Ipotesi!$B$14,AG44,"") | AU44: =IF(AND(AG44>1,AQ44>=0),AG44,"")
A45: 28 | B45: 3 | C45: =ROUND((B$13+(B$14-B$13)*4/12)*Stagionalità!$B$7,0) | D45: =C45*'Conti per prodotto'!$B$10 | E45: =C45*('Conti per prodotto'!$O$10+'Conti per prodotto'!$I$10) | F45: ='Costi B2Brand'!$E$6 | G45: =B$9 | H45: =IF(Ipotesi!$B$15="margine",MAX(0,H44-(E44-F44-G44)),0) | I45: =IF(Ipotesi!$B$15="margine",MIN(E45,F45+G45+H45+0.5*MAX(0,(E45-F45-G45)-H45)),C45*'Conti per prodotto'!$I$10) | J45: =I45-F45-G45 | K45: =K44+J45 | L45: =E45-I45 | M45: =M44+L45 | N45: =IF(IF(Ipotesi!$B$15="margine",(E45-F45-G45)/2,J45)>=Ipotesi!$B$14,A45,"") | O45: =IF(AND(A45>1,K45>=0),A45,"") | Q45: 28 | R45: 3 | S45: =ROUND((C$13+(C$14-C$13)*4/12)*Stagionalità!$B$7,0) | T45: =S45*'Conti per prodotto'!$B$10 | U45: =S45*('Conti per prodotto'!$O$10+'Conti per prodotto'!$I$10) | V45: ='Costi B2Brand'!$E$6 | W45: =C$9 | X45: =IF(Ipotesi!$B$15="margine",MAX(0,X44-(U44-V44-W44)),0) | Y45: =IF(Ipotesi!$B$15="margine",MIN(U45,V45+W45+X45+0.5*MAX(0,(U45-V45-W45)-X45)),S45*'Conti per prodotto'!$I$10) | Z45: =Y45-V45-W45 | AA45: =AA44+Z45 | AB45: =U45-Y45 | AC45: =AC44+AB45 | AD45: =IF(IF(Ipotesi!$B$15="margine",(U45-V45-W45)/2,Z45)>=Ipotesi!$B$14,Q45,"") | AE45: =IF(AND(Q45>1,AA45>=0),Q45,"") | AG45: 28 | AH45: 3 | AI45: =ROUND((D$13+(D$14-D$13)*4/12)*Stagionalità!$B$7,0) | AJ45: =AI45*'Conti per prodotto'!$B$10 | AK45: =AI45*('Conti per prodotto'!$O$10+'Conti per prodotto'!$I$10) | AL45: ='Costi B2Brand'!$E$6 | AM45: =D$9 | AN45: =IF(Ipotesi!$B$15="margine",MAX(0,AN44-(AK44-AL44-AM44)),0) | AO45: =IF(Ipotesi!$B$15="margine",MIN(AK45,AL45+AM45+AN45+0.5*MAX(0,(AK45-AL45-AM45)-AN45)),AI45*'Conti per prodotto'!$I$10) | AP45: =AO45-AL45-AM45 | AQ45: =AQ44+AP45 | AR45: =AK45-AO45 | AS45: =AS44+AR45 | AT45: =IF(IF(Ipotesi!$B$15="margine",(AK45-AL45-AM45)/2,AP45)>=Ipotesi!$B$14,AG45,"") | AU45: =IF(AND(AG45>1,AQ45>=0),AG45,"")
A46: 29 | B46: 3 | C46: =ROUND((B$13+(B$14-B$13)*5/12)*Stagionalità!$B$8,0) | D46: =C46*'Conti per prodotto'!$B$10 | E46: =C46*('Conti per prodotto'!$O$10+'Conti per prodotto'!$I$10) | F46: ='Costi B2Brand'!$E$6 | G46: =B$9 | H46: =IF(Ipotesi!$B$15="margine",MAX(0,H45-(E45-F45-G45)),0) | I46: =IF(Ipotesi!$B$15="margine",MIN(E46,F46+G46+H46+0.5*MAX(0,(E46-F46-G46)-H46)),C46*'Conti per prodotto'!$I$10) | J46: =I46-F46-G46 | K46: =K45+J46 | L46: =E46-I46 | M46: =M45+L46 | N46: =IF(IF(Ipotesi!$B$15="margine",(E46-F46-G46)/2,J46)>=Ipotesi!$B$14,A46,"") | O46: =IF(AND(A46>1,K46>=0),A46,"") | Q46: 29 | R46: 3 | S46: =ROUND((C$13+(C$14-C$13)*5/12)*Stagionalità!$B$8,0) | T46: =S46*'Conti per prodotto'!$B$10 | U46: =S46*('Conti per prodotto'!$O$10+'Conti per prodotto'!$I$10) | V46: ='Costi B2Brand'!$E$6 | W46: =C$9 | X46: =IF(Ipotesi!$B$15="margine",MAX(0,X45-(U45-V45-W45)),0) | Y46: =IF(Ipotesi!$B$15="margine",MIN(U46,V46+W46+X46+0.5*MAX(0,(U46-V46-W46)-X46)),S46*'Conti per prodotto'!$I$10) | Z46: =Y46-V46-W46 | AA46: =AA45+Z46 | AB46: =U46-Y46 | AC46: =AC45+AB46 | AD46: =IF(IF(Ipotesi!$B$15="margine",(U46-V46-W46)/2,Z46)>=Ipotesi!$B$14,Q46,"") | AE46: =IF(AND(Q46>1,AA46>=0),Q46,"") | AG46: 29 | AH46: 3 | AI46: =ROUND((D$13+(D$14-D$13)*5/12)*Stagionalità!$B$8,0) | AJ46: =AI46*'Conti per prodotto'!$B$10 | AK46: =AI46*('Conti per prodotto'!$O$10+'Conti per prodotto'!$I$10) | AL46: ='Costi B2Brand'!$E$6 | AM46: =D$9 | AN46: =IF(Ipotesi!$B$15="margine",MAX(0,AN45-(AK45-AL45-AM45)),0) | AO46: =IF(Ipotesi!$B$15="margine",MIN(AK46,AL46+AM46+AN46+0.5*MAX(0,(AK46-AL46-AM46)-AN46)),AI46*'Conti per prodotto'!$I$10) | AP46: =AO46-AL46-AM46 | AQ46: =AQ45+AP46 | AR46: =AK46-AO46 | AS46: =AS45+AR46 | AT46: =IF(IF(Ipotesi!$B$15="margine",(AK46-AL46-AM46)/2,AP46)>=Ipotesi!$B$14,AG46,"") | AU46: =IF(AND(AG46>1,AQ46>=0),AG46,"")
A47: 30 | B47: 3 | C47: =ROUND((B$13+(B$14-B$13)*6/12)*Stagionalità!$B$9,0) | D47: =C47*'Conti per prodotto'!$B$10 | E47: =C47*('Conti per prodotto'!$O$10+'Conti per prodotto'!$I$10) | F47: ='Costi B2Brand'!$E$6 | G47: =B$9 | H47: =IF(Ipotesi!$B$15="margine",MAX(0,H46-(E46-F46-G46)),0) | I47: =IF(Ipotesi!$B$15="margine",MIN(E47,F47+G47+H47+0.5*MAX(0,(E47-F47-G47)-H47)),C47*'Conti per prodotto'!$I$10) | J47: =I47-F47-G47 | K47: =K46+J47 | L47: =E47-I47 | M47: =M46+L47 | N47: =IF(IF(Ipotesi!$B$15="margine",(E47-F47-G47)/2,J47)>=Ipotesi!$B$14,A47,"") | O47: =IF(AND(A47>1,K47>=0),A47,"") | Q47: 30 | R47: 3 | S47: =ROUND((C$13+(C$14-C$13)*6/12)*Stagionalità!$B$9,0) | T47: =S47*'Conti per prodotto'!$B$10 | U47: =S47*('Conti per prodotto'!$O$10+'Conti per prodotto'!$I$10) | V47: ='Costi B2Brand'!$E$6 | W47: =C$9 | X47: =IF(Ipotesi!$B$15="margine",MAX(0,X46-(U46-V46-W46)),0) | Y47: =IF(Ipotesi!$B$15="margine",MIN(U47,V47+W47+X47+0.5*MAX(0,(U47-V47-W47)-X47)),S47*'Conti per prodotto'!$I$10) | Z47: =Y47-V47-W47 | AA47: =AA46+Z47 | AB47: =U47-Y47 | AC47: =AC46+AB47 | AD47: =IF(IF(Ipotesi!$B$15="margine",(U47-V47-W47)/2,Z47)>=Ipotesi!$B$14,Q47,"") | AE47: =IF(AND(Q47>1,AA47>=0),Q47,"") | AG47: 30 | AH47: 3 | AI47: =ROUND((D$13+(D$14-D$13)*6/12)*Stagionalità!$B$9,0) | AJ47: =AI47*'Conti per prodotto'!$B$10 | AK47: =AI47*('Conti per prodotto'!$O$10+'Conti per prodotto'!$I$10) | AL47: ='Costi B2Brand'!$E$6 | AM47: =D$9 | AN47: =IF(Ipotesi!$B$15="margine",MAX(0,AN46-(AK46-AL46-AM46)),0) | AO47: =IF(Ipotesi!$B$15="margine",MIN(AK47,AL47+AM47+AN47+0.5*MAX(0,(AK47-AL47-AM47)-AN47)),AI47*'Conti per prodotto'!$I$10) | AP47: =AO47-AL47-AM47 | AQ47: =AQ46+AP47 | AR47: =AK47-AO47 | AS47: =AS46+AR47 | AT47: =IF(IF(Ipotesi!$B$15="margine",(AK47-AL47-AM47)/2,AP47)>=Ipotesi!$B$14,AG47,"") | AU47: =IF(AND(AG47>1,AQ47>=0),AG47,"")
A48: 31 | B48: 3 | C48: =ROUND((B$13+(B$14-B$13)*7/12)*Stagionalità!$B$10,0) | D48: =C48*'Conti per prodotto'!$B$10 | E48: =C48*('Conti per prodotto'!$O$10+'Conti per prodotto'!$I$10) | F48: ='Costi B2Brand'!$E$6 | G48: =B$9 | H48: =IF(Ipotesi!$B$15="margine",MAX(0,H47-(E47-F47-G47)),0) | I48: =IF(Ipotesi!$B$15="margine",MIN(E48,F48+G48+H48+0.5*MAX(0,(E48-F48-G48)-H48)),C48*'Conti per prodotto'!$I$10) | J48: =I48-F48-G48 | K48: =K47+J48 | L48: =E48-I48 | M48: =M47+L48 | N48: =IF(IF(Ipotesi!$B$15="margine",(E48-F48-G48)/2,J48)>=Ipotesi!$B$14,A48,"") | O48: =IF(AND(A48>1,K48>=0),A48,"") | Q48: 31 | R48: 3 | S48: =ROUND((C$13+(C$14-C$13)*7/12)*Stagionalità!$B$10,0) | T48: =S48*'Conti per prodotto'!$B$10 | U48: =S48*('Conti per prodotto'!$O$10+'Conti per prodotto'!$I$10) | V48: ='Costi B2Brand'!$E$6 | W48: =C$9 | X48: =IF(Ipotesi!$B$15="margine",MAX(0,X47-(U47-V47-W47)),0) | Y48: =IF(Ipotesi!$B$15="margine",MIN(U48,V48+W48+X48+0.5*MAX(0,(U48-V48-W48)-X48)),S48*'Conti per prodotto'!$I$10) | Z48: =Y48-V48-W48 | AA48: =AA47+Z48 | AB48: =U48-Y48 | AC48: =AC47+AB48 | AD48: =IF(IF(Ipotesi!$B$15="margine",(U48-V48-W48)/2,Z48)>=Ipotesi!$B$14,Q48,"") | AE48: =IF(AND(Q48>1,AA48>=0),Q48,"") | AG48: 31 | AH48: 3 | AI48: =ROUND((D$13+(D$14-D$13)*7/12)*Stagionalità!$B$10,0) | AJ48: =AI48*'Conti per prodotto'!$B$10 | AK48: =AI48*('Conti per prodotto'!$O$10+'Conti per prodotto'!$I$10) | AL48: ='Costi B2Brand'!$E$6 | AM48: =D$9 | AN48: =IF(Ipotesi!$B$15="margine",MAX(0,AN47-(AK47-AL47-AM47)),0) | AO48: =IF(Ipotesi!$B$15="margine",MIN(AK48,AL48+AM48+AN48+0.5*MAX(0,(AK48-AL48-AM48)-AN48)),AI48*'Conti per prodotto'!$I$10) | AP48: =AO48-AL48-AM48 | AQ48: =AQ47+AP48 | AR48: =AK48-AO48 | AS48: =AS47+AR48 | AT48: =IF(IF(Ipotesi!$B$15="margine",(AK48-AL48-AM48)/2,AP48)>=Ipotesi!$B$14,AG48,"") | AU48: =IF(AND(AG48>1,AQ48>=0),AG48,"")
A49: 32 | B49: 3 | C49: =ROUND((B$13+(B$14-B$13)*8/12)*Stagionalità!$B$11,0) | D49: =C49*'Conti per prodotto'!$B$10 | E49: =C49*('Conti per prodotto'!$O$10+'Conti per prodotto'!$I$10) | F49: ='Costi B2Brand'!$E$6 | G49: =B$9 | H49: =IF(Ipotesi!$B$15="margine",MAX(0,H48-(E48-F48-G48)),0) | I49: =IF(Ipotesi!$B$15="margine",MIN(E49,F49+G49+H49+0.5*MAX(0,(E49-F49-G49)-H49)),C49*'Conti per prodotto'!$I$10) | J49: =I49-F49-G49 | K49: =K48+J49 | L49: =E49-I49 | M49: =M48+L49 | N49: =IF(IF(Ipotesi!$B$15="margine",(E49-F49-G49)/2,J49)>=Ipotesi!$B$14,A49,"") | O49: =IF(AND(A49>1,K49>=0),A49,"") | Q49: 32 | R49: 3 | S49: =ROUND((C$13+(C$14-C$13)*8/12)*Stagionalità!$B$11,0) | T49: =S49*'Conti per prodotto'!$B$10 | U49: =S49*('Conti per prodotto'!$O$10+'Conti per prodotto'!$I$10) | V49: ='Costi B2Brand'!$E$6 | W49: =C$9 | X49: =IF(Ipotesi!$B$15="margine",MAX(0,X48-(U48-V48-W48)),0) | Y49: =IF(Ipotesi!$B$15="margine",MIN(U49,V49+W49+X49+0.5*MAX(0,(U49-V49-W49)-X49)),S49*'Conti per prodotto'!$I$10) | Z49: =Y49-V49-W49 | AA49: =AA48+Z49 | AB49: =U49-Y49 | AC49: =AC48+AB49 | AD49: =IF(IF(Ipotesi!$B$15="margine",(U49-V49-W49)/2,Z49)>=Ipotesi!$B$14,Q49,"") | AE49: =IF(AND(Q49>1,AA49>=0),Q49,"") | AG49: 32 | AH49: 3 | AI49: =ROUND((D$13+(D$14-D$13)*8/12)*Stagionalità!$B$11,0) | AJ49: =AI49*'Conti per prodotto'!$B$10 | AK49: =AI49*('Conti per prodotto'!$O$10+'Conti per prodotto'!$I$10) | AL49: ='Costi B2Brand'!$E$6 | AM49: =D$9 | AN49: =IF(Ipotesi!$B$15="margine",MAX(0,AN48-(AK48-AL48-AM48)),0) | AO49: =IF(Ipotesi!$B$15="margine",MIN(AK49,AL49+AM49+AN49+0.5*MAX(0,(AK49-AL49-AM49)-AN49)),AI49*'Conti per prodotto'!$I$10) | AP49: =AO49-AL49-AM49 | AQ49: =AQ48+AP49 | AR49: =AK49-AO49 | AS49: =AS48+AR49 | AT49: =IF(IF(Ipotesi!$B$15="margine",(AK49-AL49-AM49)/2,AP49)>=Ipotesi!$B$14,AG49,"") | AU49: =IF(AND(AG49>1,AQ49>=0),AG49,"")
A50: 33 | B50: 3 | C50: =ROUND((B$13+(B$14-B$13)*9/12)*Stagionalità!$B$12,0) | D50: =C50*'Conti per prodotto'!$B$10 | E50: =C50*('Conti per prodotto'!$O$10+'Conti per prodotto'!$I$10) | F50: ='Costi B2Brand'!$E$6 | G50: =B$9 | H50: =IF(Ipotesi!$B$15="margine",MAX(0,H49-(E49-F49-G49)),0) | I50: =IF(Ipotesi!$B$15="margine",MIN(E50,F50+G50+H50+0.5*MAX(0,(E50-F50-G50)-H50)),C50*'Conti per prodotto'!$I$10) | J50: =I50-F50-G50 | K50: =K49+J50 | L50: =E50-I50 | M50: =M49+L50 | N50: =IF(IF(Ipotesi!$B$15="margine",(E50-F50-G50)/2,J50)>=Ipotesi!$B$14,A50,"") | O50: =IF(AND(A50>1,K50>=0),A50,"") | Q50: 33 | R50: 3 | S50: =ROUND((C$13+(C$14-C$13)*9/12)*Stagionalità!$B$12,0) | T50: =S50*'Conti per prodotto'!$B$10 | U50: =S50*('Conti per prodotto'!$O$10+'Conti per prodotto'!$I$10) | V50: ='Costi B2Brand'!$E$6 | W50: =C$9 | X50: =IF(Ipotesi!$B$15="margine",MAX(0,X49-(U49-V49-W49)),0) | Y50: =IF(Ipotesi!$B$15="margine",MIN(U50,V50+W50+X50+0.5*MAX(0,(U50-V50-W50)-X50)),S50*'Conti per prodotto'!$I$10) | Z50: =Y50-V50-W50 | AA50: =AA49+Z50 | AB50: =U50-Y50 | AC50: =AC49+AB50 | AD50: =IF(IF(Ipotesi!$B$15="margine",(U50-V50-W50)/2,Z50)>=Ipotesi!$B$14,Q50,"") | AE50: =IF(AND(Q50>1,AA50>=0),Q50,"") | AG50: 33 | AH50: 3 | AI50: =ROUND((D$13+(D$14-D$13)*9/12)*Stagionalità!$B$12,0) | AJ50: =AI50*'Conti per prodotto'!$B$10 | AK50: =AI50*('Conti per prodotto'!$O$10+'Conti per prodotto'!$I$10) | AL50: ='Costi B2Brand'!$E$6 | AM50: =D$9 | AN50: =IF(Ipotesi!$B$15="margine",MAX(0,AN49-(AK49-AL49-AM49)),0) | AO50: =IF(Ipotesi!$B$15="margine",MIN(AK50,AL50+AM50+AN50+0.5*MAX(0,(AK50-AL50-AM50)-AN50)),AI50*'Conti per prodotto'!$I$10) | AP50: =AO50-AL50-AM50 | AQ50: =AQ49+AP50 | AR50: =AK50-AO50 | AS50: =AS49+AR50 | AT50: =IF(IF(Ipotesi!$B$15="margine",(AK50-AL50-AM50)/2,AP50)>=Ipotesi!$B$14,AG50,"") | AU50: =IF(AND(AG50>1,AQ50>=0),AG50,"")
A51: 34 | B51: 3 | C51: =ROUND((B$13+(B$14-B$13)*10/12)*Stagionalità!$B$13,0) | D51: =C51*'Conti per prodotto'!$B$10 | E51: =C51*('Conti per prodotto'!$O$10+'Conti per prodotto'!$I$10) | F51: ='Costi B2Brand'!$E$6 | G51: =B$9 | H51: =IF(Ipotesi!$B$15="margine",MAX(0,H50-(E50-F50-G50)),0) | I51: =IF(Ipotesi!$B$15="margine",MIN(E51,F51+G51+H51+0.5*MAX(0,(E51-F51-G51)-H51)),C51*'Conti per prodotto'!$I$10) | J51: =I51-F51-G51 | K51: =K50+J51 | L51: =E51-I51 | M51: =M50+L51 | N51: =IF(IF(Ipotesi!$B$15="margine",(E51-F51-G51)/2,J51)>=Ipotesi!$B$14,A51,"") | O51: =IF(AND(A51>1,K51>=0),A51,"") | Q51: 34 | R51: 3 | S51: =ROUND((C$13+(C$14-C$13)*10/12)*Stagionalità!$B$13,0) | T51: =S51*'Conti per prodotto'!$B$10 | U51: =S51*('Conti per prodotto'!$O$10+'Conti per prodotto'!$I$10) | V51: ='Costi B2Brand'!$E$6 | W51: =C$9 | X51: =IF(Ipotesi!$B$15="margine",MAX(0,X50-(U50-V50-W50)),0) | Y51: =IF(Ipotesi!$B$15="margine",MIN(U51,V51+W51+X51+0.5*MAX(0,(U51-V51-W51)-X51)),S51*'Conti per prodotto'!$I$10) | Z51: =Y51-V51-W51 | AA51: =AA50+Z51 | AB51: =U51-Y51 | AC51: =AC50+AB51 | AD51: =IF(IF(Ipotesi!$B$15="margine",(U51-V51-W51)/2,Z51)>=Ipotesi!$B$14,Q51,"") | AE51: =IF(AND(Q51>1,AA51>=0),Q51,"") | AG51: 34 | AH51: 3 | AI51: =ROUND((D$13+(D$14-D$13)*10/12)*Stagionalità!$B$13,0) | AJ51: =AI51*'Conti per prodotto'!$B$10 | AK51: =AI51*('Conti per prodotto'!$O$10+'Conti per prodotto'!$I$10) | AL51: ='Costi B2Brand'!$E$6 | AM51: =D$9 | AN51: =IF(Ipotesi!$B$15="margine",MAX(0,AN50-(AK50-AL50-AM50)),0) | AO51: =IF(Ipotesi!$B$15="margine",MIN(AK51,AL51+AM51+AN51+0.5*MAX(0,(AK51-AL51-AM51)-AN51)),AI51*'Conti per prodotto'!$I$10) | AP51: =AO51-AL51-AM51 | AQ51: =AQ50+AP51 | AR51: =AK51-AO51 | AS51: =AS50+AR51 | AT51: =IF(IF(Ipotesi!$B$15="margine",(AK51-AL51-AM51)/2,AP51)>=Ipotesi!$B$14,AG51,"") | AU51: =IF(AND(AG51>1,AQ51>=0),AG51,"")
A52: 35 | B52: 3 | C52: =ROUND((B$13+(B$14-B$13)*11/12)*Stagionalità!$B$2,0) | D52: =C52*'Conti per prodotto'!$B$10 | E52: =C52*('Conti per prodotto'!$O$10+'Conti per prodotto'!$I$10) | F52: ='Costi B2Brand'!$E$6 | G52: =B$9 | H52: =IF(Ipotesi!$B$15="margine",MAX(0,H51-(E51-F51-G51)),0) | I52: =IF(Ipotesi!$B$15="margine",MIN(E52,F52+G52+H52+0.5*MAX(0,(E52-F52-G52)-H52)),C52*'Conti per prodotto'!$I$10) | J52: =I52-F52-G52 | K52: =K51+J52 | L52: =E52-I52 | M52: =M51+L52 | N52: =IF(IF(Ipotesi!$B$15="margine",(E52-F52-G52)/2,J52)>=Ipotesi!$B$14,A52,"") | O52: =IF(AND(A52>1,K52>=0),A52,"") | Q52: 35 | R52: 3 | S52: =ROUND((C$13+(C$14-C$13)*11/12)*Stagionalità!$B$2,0) | T52: =S52*'Conti per prodotto'!$B$10 | U52: =S52*('Conti per prodotto'!$O$10+'Conti per prodotto'!$I$10) | V52: ='Costi B2Brand'!$E$6 | W52: =C$9 | X52: =IF(Ipotesi!$B$15="margine",MAX(0,X51-(U51-V51-W51)),0) | Y52: =IF(Ipotesi!$B$15="margine",MIN(U52,V52+W52+X52+0.5*MAX(0,(U52-V52-W52)-X52)),S52*'Conti per prodotto'!$I$10) | Z52: =Y52-V52-W52 | AA52: =AA51+Z52 | AB52: =U52-Y52 | AC52: =AC51+AB52 | AD52: =IF(IF(Ipotesi!$B$15="margine",(U52-V52-W52)/2,Z52)>=Ipotesi!$B$14,Q52,"") | AE52: =IF(AND(Q52>1,AA52>=0),Q52,"") | AG52: 35 | AH52: 3 | AI52: =ROUND((D$13+(D$14-D$13)*11/12)*Stagionalità!$B$2,0) | AJ52: =AI52*'Conti per prodotto'!$B$10 | AK52: =AI52*('Conti per prodotto'!$O$10+'Conti per prodotto'!$I$10) | AL52: ='Costi B2Brand'!$E$6 | AM52: =D$9 | AN52: =IF(Ipotesi!$B$15="margine",MAX(0,AN51-(AK51-AL51-AM51)),0) | AO52: =IF(Ipotesi!$B$15="margine",MIN(AK52,AL52+AM52+AN52+0.5*MAX(0,(AK52-AL52-AM52)-AN52)),AI52*'Conti per prodotto'!$I$10) | AP52: =AO52-AL52-AM52 | AQ52: =AQ51+AP52 | AR52: =AK52-AO52 | AS52: =AS51+AR52 | AT52: =IF(IF(Ipotesi!$B$15="margine",(AK52-AL52-AM52)/2,AP52)>=Ipotesi!$B$14,AG52,"") | AU52: =IF(AND(AG52>1,AQ52>=0),AG52,"")
A53: 36 | B53: 3 | C53: =ROUND((B$13+(B$14-B$13)*12/12)*Stagionalità!$B$3,0) | D53: =C53*'Conti per prodotto'!$B$10 | E53: =C53*('Conti per prodotto'!$O$10+'Conti per prodotto'!$I$10) | F53: ='Costi B2Brand'!$E$6 | G53: =B$9 | H53: =IF(Ipotesi!$B$15="margine",MAX(0,H52-(E52-F52-G52)),0) | I53: =IF(Ipotesi!$B$15="margine",MIN(E53,F53+G53+H53+0.5*MAX(0,(E53-F53-G53)-H53)),C53*'Conti per prodotto'!$I$10) | J53: =I53-F53-G53 | K53: =K52+J53 | L53: =E53-I53 | M53: =M52+L53 | N53: =IF(IF(Ipotesi!$B$15="margine",(E53-F53-G53)/2,J53)>=Ipotesi!$B$14,A53,"") | O53: =IF(AND(A53>1,K53>=0),A53,"") | Q53: 36 | R53: 3 | S53: =ROUND((C$13+(C$14-C$13)*12/12)*Stagionalità!$B$3,0) | T53: =S53*'Conti per prodotto'!$B$10 | U53: =S53*('Conti per prodotto'!$O$10+'Conti per prodotto'!$I$10) | V53: ='Costi B2Brand'!$E$6 | W53: =C$9 | X53: =IF(Ipotesi!$B$15="margine",MAX(0,X52-(U52-V52-W52)),0) | Y53: =IF(Ipotesi!$B$15="margine",MIN(U53,V53+W53+X53+0.5*MAX(0,(U53-V53-W53)-X53)),S53*'Conti per prodotto'!$I$10) | Z53: =Y53-V53-W53 | AA53: =AA52+Z53 | AB53: =U53-Y53 | AC53: =AC52+AB53 | AD53: =IF(IF(Ipotesi!$B$15="margine",(U53-V53-W53)/2,Z53)>=Ipotesi!$B$14,Q53,"") | AE53: =IF(AND(Q53>1,AA53>=0),Q53,"") | AG53: 36 | AH53: 3 | AI53: =ROUND((D$13+(D$14-D$13)*12/12)*Stagionalità!$B$3,0) | AJ53: =AI53*'Conti per prodotto'!$B$10 | AK53: =AI53*('Conti per prodotto'!$O$10+'Conti per prodotto'!$I$10) | AL53: ='Costi B2Brand'!$E$6 | AM53: =D$9 | AN53: =IF(Ipotesi!$B$15="margine",MAX(0,AN52-(AK52-AL52-AM52)),0) | AO53: =IF(Ipotesi!$B$15="margine",MIN(AK53,AL53+AM53+AN53+0.5*MAX(0,(AK53-AL53-AM53)-AN53)),AI53*'Conti per prodotto'!$I$10) | AP53: =AO53-AL53-AM53 | AQ53: =AQ52+AP53 | AR53: =AK53-AO53 | AS53: =AS52+AR53 | AT53: =IF(IF(Ipotesi!$B$15="margine",(AK53-AL53-AM53)/2,AP53)>=Ipotesi!$B$14,AG53,"") | AU53: =IF(AND(AG53>1,AQ53>=0),AG53,"")
A55: Ordini anno 1 / 2 / 3 | D55: =SUM(C18:C29) | E55: =SUM(C30:C41) | F55: =SUM(C42:C53) | Q55: Ordini anno 1 / 2 / 3 | T55: =SUM(S18:S29) | U55: =SUM(S30:S41) | V55: =SUM(S42:S53) | AG55: Ordini anno 1 / 2 / 3 | AJ55: =SUM(AI18:AI29) | AK55: =SUM(AI30:AI41) | AL55: =SUM(AI42:AI53)
A56: Vendite online anno 1 / 2 / 3 | D56: =SUM(D18:D29) | E56: =SUM(D30:D41) | F56: =SUM(D42:D53) | Q56: Vendite online anno 1 / 2 / 3 | T56: =SUM(T18:T29) | U56: =SUM(T30:T41) | V56: =SUM(T42:T53) | AG56: Vendite online anno 1 / 2 / 3 | AJ56: =SUM(AJ18:AJ29) | AK56: =SUM(AJ30:AJ41) | AL56: =SUM(AJ42:AJ53)
A57: Netto B2Brand anno 1 / 2 / 3 | D57: =SUM(J18:J29) | E57: =SUM(J30:J41) | F57: =SUM(J42:J53) | Q57: Netto B2Brand anno 1 / 2 / 3 | T57: =SUM(Z18:Z29) | U57: =SUM(Z30:Z41) | V57: =SUM(Z42:Z53) | AG57: Netto B2Brand anno 1 / 2 / 3 | AJ57: =SUM(AP18:AP29) | AK57: =SUM(AP30:AP41) | AL57: =SUM(AP42:AP53)
A58: …al mese | D58: =SUM(J18:J29)/12 | E58: =SUM(J30:J41)/12 | F58: =SUM(J42:J53)/12 | Q58: …al mese | T58: =SUM(Z18:Z29)/12 | U58: =SUM(Z30:Z41)/12 | V58: =SUM(Z42:Z53)/12 | AG58: …al mese | AJ58: =SUM(AP18:AP29)/12 | AK58: =SUM(AP30:AP41)/12 | AL58: =SUM(AP42:AP53)/12
A59: Netto Kalab anno 1 / 2 / 3 | D59: =SUM(L18:L29) | E59: =SUM(L30:L41) | F59: =SUM(L42:L53) | Q59: Netto Kalab anno 1 / 2 / 3 | T59: =SUM(AB18:AB29) | U59: =SUM(AB30:AB41) | V59: =SUM(AB42:AB53) | AG59: Netto Kalab anno 1 / 2 / 3 | AJ59: =SUM(AR18:AR29) | AK59: =SUM(AR30:AR41) | AL59: =SUM(AR42:AR53)
A60: …al mese | D60: =SUM(L18:L29)/12 | E60: =SUM(L30:L41)/12 | F60: =SUM(L42:L53)/12 | Q60: …al mese | T60: =SUM(AB18:AB29)/12 | U60: =SUM(AB30:AB41)/12 | V60: =SUM(AB42:AB53)/12 | AG60: …al mese | AJ60: =SUM(AR18:AR29)/12 | AK60: =SUM(AR30:AR41)/12 | AL60: =SUM(AR42:AR53)/12
A61: Primo mese a quota obiettivo (con «margine»: metà del guadagno del mese) | D61: =IF(MIN(N18:N53)=0,"oltre 36",MIN(N18:N53)) | Q61: Primo mese a quota obiettivo (con «margine»: metà del guadagno del mese) | T61: =IF(MIN(AD18:AD53)=0,"oltre 36",MIN(AD18:AD53)) | AG61: Primo mese a quota obiettivo (con «margine»: metà del guadagno del mese) | AJ61: =IF(MIN(AT18:AT53)=0,"oltre 36",MIN(AT18:AT53))
A62: Primo mese col cumulato B2Brand ≥ 0 | D62: =IF(MIN(O18:O53)=0,"oltre 36",MIN(O18:O53)) | Q62: Primo mese col cumulato B2Brand ≥ 0 | T62: =IF(MIN(AE18:AE53)=0,"oltre 36",MIN(AE18:AE53)) | AG62: Primo mese col cumulato B2Brand ≥ 0 | AJ62: =IF(MIN(AU18:AU53)=0,"oltre 36",MIN(AU18:AU53))
A63: Massimo che B2Brand ha «fuori» (€) | D63: =MIN(0,MIN(K18:K53)) | Q63: Massimo che B2Brand ha «fuori» (€) | T63: =MIN(0,MIN(AA18:AA53)) | AG63: Massimo che B2Brand ha «fuori» (€) | AJ63: =MIN(0,MIN(AQ18:AQ53))

Sheet Equilibrio
A1: Dove B2Brand e Kalab prendono la stessa cifra
A2: Margine da dividere per ordine (€): merce netta meno prodotto, imballo, spedizione non pagata dal cliente, commissioni e perdite | F2: =('Conti per prodotto'!$O$10+'Conti per prodotto'!$I$10)
A3: Merce netta per ordine (€): senza IVA e senza commissioni | F3: ='Conti per prodotto'!$G$10
A5: Ordini al mese | B5: Pubblicità al mese (€) | C5: Spese fisse B2Brand (€) | D5: % della merce netta che pareggia | E5: € a testa al mese (= metà del margine) | F5: Con la percentuale fissa delle Ipotesi: B2Brand (€) | G5: …e Kalab (€)
A6: 50 | B6: 300 | C6: ='Costi B2Brand'!$C$6+B6 | D6: =$F$2/(2*$F$3)+C6/(2*$F$3*A6) | E6: =($F$2*A6-C6)/2 | F6: =A6*'Conti per prodotto'!$I$10-C6 | G6: =A6*'Conti per prodotto'!$O$10
A7: 100 | B7: 400 | C7: ='Costi B2Brand'!$C$6+B7 | D7: =$F$2/(2*$F$3)+C7/(2*$F$3*A7) | E7: =($F$2*A7-C7)/2 | F7: =A7*'Conti per prodotto'!$I$10-C7 | G7: =A7*'Conti per prodotto'!$O$10
A8: 150 | B8: 400 | C8: ='Costi B2Brand'!$C$6+B8 | D8: =$F$2/(2*$F$3)+C8/(2*$F$3*A8) | E8: =($F$2*A8-C8)/2 | F8: =A8*'Conti per prodotto'!$I$10-C8 | G8: =A8*'Conti per prodotto'!$O$10
A9: 200 | B9: 500 | C9: ='Costi B2Brand'!$C$6+B9 | D9: =$F$2/(2*$F$3)+C9/(2*$F$3*A9) | E9: =($F$2*A9-C9)/2 | F9: =A9*'Conti per prodotto'!$I$10-C9 | G9: =A9*'Conti per prodotto'!$O$10
A10: 300 | B10: 600 | C10: ='Costi B2Brand'!$C$6+B10 | D10: =$F$2/(2*$F$3)+C10/(2*$F$3*A10) | E10: =($F$2*A10-C10)/2 | F10: =A10*'Conti per prodotto'!$I$10-C10 | G10: =A10*'Conti per prodotto'!$O$10
A11: 500 | B11: 800 | C11: ='Costi B2Brand'!$C$6+B11 | D11: =$F$2/(2*$F$3)+C11/(2*$F$3*A11) | E11: =($F$2*A11-C11)/2 | F11: =A11*'Conti per prodotto'!$I$10-C11 | G11: =A11*'Conti per prodotto'!$O$10
A13: Lettura: B2Brand paga pubblicità e piattaforma, che costano uguale con pochi o tanti ordini; Kalab paga prodotto e spedizione, che crescono con gli ordini. Per questo la percentuale fissa che pareggia scende quando i volumi salgono. «Metà del margine» pareggia a ogni volume senza toccare niente.

Sheet Ambizioso - cosa serve
A1: Scenario ambizioso: cosa deve succedere ogni mese, a regime, per arrivarci
A2: Celle azzurre = valori di riferimento dai benchmark (fonte in ricerca/ambizioso/02_benchmark_e_numeri.md). Ordini e pubblicità arrivano dal foglio Scenari, colonna Ambizioso.
A4: Voce | B4: Anno 1 | C4: Anno 2 | D4: Anno 3 | E4: Nota
A5: Tasso di conversione del sito | B5: 0.012 | C5: 0.016 | D5: 0.019 | E5: da 0,8% (negozio nuovo) a 2,2%; mediana piccoli Shopify 1,4% (Littledata 09/2026); Food & Drink UK 1,58% (IRP 08/2026) — 02 §1.1 e §3
A6: Ordini da clienti che ritornano | B6: 0.25 | C6: 0.28 | D6: 0.35 | E6: riacquisto medio simulato (02 §2.3): nei prodotti di consumo ricompra entro un anno il 30-40% dei clienti
A7: Costo di un clic a pagamento (€) | B7: 0.7 | C7: 0.7 | D7: 0.7 | E7: clic medio fra Google Shopping (~0,55 €) e Meta (~1 €) — 05 §5, 02 §2.1
A8: Costo pubblicitario per un cliente nuovo (€) | B8: 35 | C8: 35 | D8: 35 | E8: benchmark food 25-50 € (02 §1.5); sostenibile ≤ 20 € con ordine medio 28 €, ≤ 29 € con 40 €
A9: Quota degli ordini dalla newsletter | B9: 0.13 | C9: 0.16 | D9: 0.2 | E9: simulazione 02 §2.4 (13-23%); media degli account Klaviyo 19% del fatturato
A10: Ordini al mese ogni 1.000 iscritti | B10: 8.5 | C10: 8.5 | D10: 8.5 | E10: 4 campagne al mese × 0,17% + benvenuto e carrelli (02 §2.1 e §2.4)
A12: Ordini al mese (obiettivo a regime) | B12: =Scenari!$D$3 | C12: =Scenari!$D$4 | D12: =Scenari!$D$5
A13: Pubblicità al mese (€) | B13: =Scenari!$D$7 | C13: =Scenari!$D$8 | D13: =Scenari!$D$9
A14: Visite al mese necessarie | B14: =ROUND(B12/B5,0) | C14: =ROUND(C12/C5,0) | D14: =ROUND(D12/D5,0)
A15: …di cui comprate con la pubblicità | B15: =ROUND(B13/B7,0) | C15: =ROUND(C13/C7,0) | D15: =ROUND(D13/D7,0)
A16: …di cui da portare gratis (Google, social, eventi, passaparola) | B16: =MAX(0,B14-B15) | C16: =MAX(0,C14-C15) | D16: =MAX(0,D14-D15)
A17: Clienti nuovi al mese | B17: =ROUND(B12*(1-B6),0) | C17: =ROUND(C12*(1-C6),0) | D17: =ROUND(D12*(1-D6),0)
A18: …di cui comprati con la pubblicità | B18: =ROUND(B13/B8,0) | C18: =ROUND(C13/C8,0) | D18: =ROUND(D13/D8,0)
A19: …di cui da trovare gratis | B19: =MAX(0,B17-B18) | C19: =MAX(0,C17-C18) | D19: =MAX(0,D17-D18)
A20: Ordini di clienti che ritornano | B20: =ROUND(B12*B6,0) | C20: =ROUND(C12*C6,0) | D20: =ROUND(D12*D6,0)
A21: Ordini dalla newsletter | B21: =ROUND(B12*B9,0) | C21: =ROUND(C12*C9,0) | D21: =ROUND(D12*D9,0)
A22: Iscritti alla newsletter necessari | B22: =ROUND(B21/B10*1000,0) | C22: =ROUND(C21/C10*1000,0) | D22: =ROUND(D21/D10*1000,0)
A23: Ordini al giorno | B23: =ROUND(B12/30,1) | C23: =ROUND(C12/30,1) | D23: =ROUND(D12/30,1)
A25: Lettura: la riga «da portare gratis» è il lavoro vero del marchio. Se è troppo alta rispetto a quello che Google, social, eventi e B2B possono dare, l'ambizioso non si raggiunge con quella pubblicità.

Sheet Logistica
A1: Corsa pomeridiana all'hub contro magazzino conto terzi (3PL), per prodotti non deperibili
A3: Km di andata Scalea → hub (Battipaglia) | B3: 149 | C3: rome2rio, 149 km, 1 h 44 (letto il 04/10/2026)
A4: Ore di guida di andata | B4: 1.75 | C4: rome2rio 1 h 44; arrotondato
A5: Carburante di andata (€) | B5: 30 | C5: rome2rio 24-35 € a tratta
A6: Usura, gomme, manutenzione (€/km) | B6: 0.1 | C6: STIMA
A7: Ore al deposito (consegna pacchi) | B7: 0.5 | C7: STIMA
A8: Corse al mese | B8: 22 | C8: una ogni giorno lavorativo
A9: Valore di un'ora di chi guida (€) | B9: 15 | C9: IPOTESI: un'ora tolta al campo o al laboratorio
A10: 3PL: picking + packing per ordine (€) | B10: 2 | C10: Tissquad 01/04/2026: picking 0,80-1,50 + packing 0,50-1,00
A11: 3PL: materiali per pacco (€) | B11: 0.75 | C11: Tissquad: 0,50-1,00
A12: 3PL: costo di un pallet al mese (€) | B12: 40 | C12: Tissquad: 25-50 €/pallet/mese
A13: 3PL: pallet occupati | B13: 2 | C13: IPOTESI: 2 pallet di vasetti bastano per 2-3 mesi
A14: 3PL: rifornimento al mese da Scalea (€) | B14: 90 | C14: STIMA: una corsa al mese o un bancale col corriere
A15: 3PL: spedizione dall'hub, 0-2 kg (€) | B15: 5 | C15: Tissquad: Nord 3,50-5,00; da Scalea oggi 7-7,50 (03)
A17: Una corsa (andata e ritorno): euro | B17: =2*Logistica!$B$5+2*Logistica!$B$3*Logistica!$B$6
A18: Una corsa: ore | B18: =2*Logistica!$B$4+Logistica!$B$7
A19: Al mese: euro / ore | B19: =B17*Logistica!$B$8 | C19: =B18*Logistica!$B$8
A21: Ordini al mese | B21: Corsa: € per ordine | C21: Corsa con il tempo: € per ordine | D21: 3PL: € per ordine | E21: 3PL meno risparmio di spedizione e imballo
A22: 50 | B22: =Logistica!$B$19/A22 | C22: =(Logistica!$B$19+Logistica!$C$19*Logistica!$B$9)/A22 | D22: =Logistica!$B$10+Logistica!$B$11+(Logistica!$B$12*Logistica!$B$13+Logistica!$B$14)/A22 | E22: =D22-('Conti per prodotto'!$M$10-Logistica!$B$15)-'Conti per prodotto'!$L$10
A23: 100 | B23: =Logistica!$B$19/A23 | C23: =(Logistica!$B$19+Logistica!$C$19*Logistica!$B$9)/A23 | D23: =Logistica!$B$10+Logistica!$B$11+(Logistica!$B$12*Logistica!$B$13+Logistica!$B$14)/A23 | E23: =D23-('Conti per prodotto'!$M$10-Logistica!$B$15)-'Conti per prodotto'!$L$10
A24: 150 | B24: =Logistica!$B$19/A24 | C24: =(Logistica!$B$19+Logistica!$C$19*Logistica!$B$9)/A24 | D24: =Logistica!$B$10+Logistica!$B$11+(Logistica!$B$12*Logistica!$B$13+Logistica!$B$14)/A24 | E24: =D24-('Conti per prodotto'!$M$10-Logistica!$B$15)-'Conti per prodotto'!$L$10
A25: 300 | B25: =Logistica!$B$19/A25 | C25: =(Logistica!$B$19+Logistica!$C$19*Logistica!$B$9)/A25 | D25: =Logistica!$B$10+Logistica!$B$11+(Logistica!$B$12*Logistica!$B$13+Logistica!$B$14)/A25 | E25: =D25-('Conti per prodotto'!$M$10-Logistica!$B$15)-'Conti per prodotto'!$L$10
A26: 600 | B26: =Logistica!$B$19/A26 | C26: =(Logistica!$B$19+Logistica!$C$19*Logistica!$B$9)/A26 | D26: =Logistica!$B$10+Logistica!$B$11+(Logistica!$B$12*Logistica!$B$13+Logistica!$B$14)/A26 | E26: =D26-('Conti per prodotto'!$M$10-Logistica!$B$15)-'Conti per prodotto'!$L$10
A27: 1000 | B27: =Logistica!$B$19/A27 | C27: =(Logistica!$B$19+Logistica!$C$19*Logistica!$B$9)/A27 | D27: =Logistica!$B$10+Logistica!$B$11+(Logistica!$B$12*Logistica!$B$13+Logistica!$B$14)/A27 | E27: =D27-('Conti per prodotto'!$M$10-Logistica!$B$15)-'Conti per prodotto'!$L$10
A29: Lettura: la corsa costa uguale con 50 o con 1.000 ordini, quindi pesa per ordine solo quando i volumi sono alti. Il 3PL costa per ordine ma toglie l'imballo e la spedizione da Calabria (più cara e con un giorno in più). Colonna E: costo netto del 3PL rispetto a spedire da Scalea; vicino a zero = conviene già.

Sheet Confronto accordi
A1: Cosa succede a un ordine medio con diversi accordi (scenario medio, anno 1)
A2: Accordo | B2: Base (lordo/netto) | C2: Quota % | D2: B2Brand per ordine (€) | E2: Kalab margine per ordine (€) | F2: Kalab margine % prezzo | G2: Commento
A3: 50% dell'incasso lordo (proposta di Kalab) | B3: lordo | C3: 0.5 | D3: =IF(B3="lordo",'Conti per prodotto'!$H$10,'Conti per prodotto'!$G$10)*C3 | E3: ='Conti per prodotto'!$O$10+'Conti per prodotto'!$I$10-D3 | F3: =E3/'Conti per prodotto'!$B$10 | G3: Quota su merce + spedizione incassata, IVA inclusa: la lettura letterale di «50% dell'incasso».
A4: 50% dell'incassato netto (senza IVA, spedizione e commissioni) | B4: netto | C4: 0.5 | D4: =IF(B4="lordo",'Conti per prodotto'!$H$10,'Conti per prodotto'!$G$10)*C4 | E4: ='Conti per prodotto'!$O$10+'Conti per prodotto'!$I$10-D4 | F4: =E4/'Conti per prodotto'!$B$10 | G4: Stessa percentuale, base più piccola: è la prassi del settore (07 B1e).
A5: 40% dell'incassato netto | B5: netto | C5: 0.4 | D5: =IF(B5="lordo",'Conti per prodotto'!$H$10,'Conti per prodotto'!$G$10)*C5 | E5: ='Conti per prodotto'!$O$10+'Conti per prodotto'!$I$10-D5 | F5: =E5/'Conti per prodotto'!$B$10 | G5: Primo scaglione proposto: fino al rientro documentato dell'anticipo di B2Brand.
A6: 30% dell'incassato netto | B6: netto | C6: 0.3 | D6: =IF(B6="lordo",'Conti per prodotto'!$H$10,'Conti per prodotto'!$G$10)*C6 | E6: ='Conti per prodotto'!$O$10+'Conti per prodotto'!$I$10-D6 | F6: =E6/'Conti per prodotto'!$B$10 | G6: Secondo scaglione, dopo il rientro. Fascia alta dell'outsourcing italiano (15-30%, 07).
A7: 20% dell'incassato netto | B7: netto | C7: 0.2 | D7: =IF(B7="lordo",'Conti per prodotto'!$H$10,'Conti per prodotto'!$G$10)*C7 | E7: ='Conti per prodotto'!$O$10+'Conti per prodotto'!$I$10-D7 | F7: =E7/'Conti per prodotto'!$B$10 | G7: Terzo scaglione sopra una soglia annua. Sotto, B2Brand non copre nemmeno le ore.
A8: 10% netto sugli ordini B2B passati dal sito | B8: netto | C8: 0.1 | D8: =IF(B8="lordo",'Conti per prodotto'!$H$10,'Conti per prodotto'!$G$10)*C8 | E8: ='Conti per prodotto'!$O$10+'Conti per prodotto'!$I$10-D8 | F8: =E8/'Conti per prodotto'!$B$10 | G8: Per ristoranti, bar e botteghe che ordinano dal sito con listino riservato: volumi alti, margine basso.
A10: Lettura: l'ordine medio è quello del foglio Conti (mix di categorie). Il margine di Kalab è dopo prodotto, imballo, spedizione vera e perdite. Per vedere l'effetto sui 36 mesi, cambiare quota e base nel foglio Ipotesi.
